Workbook
Name CV: 參數!$B$4
Name SL_Z_Table: [1]參數!$D$2:$F$6
Name W: 參數!$B$2
Name ZTable: 參數!$D$2:$F$5

Sheet 整合資料
A1: 物料編號 | B1: 品名 | C1: 2023年5月 | D1: 2023年6月 | E1: 2023年7月 | F1: 2023年8月 | G1: 2023年9月 | H1: 2023年10月 | I1: 2023年11月 | J1: 2023年12月 | K1: 2024年1月 | L1: 2024年2月 | M1: 2024年3月 | N1: 2024年4月 | O1: 2024年5月 | P1: 2024年6月 | Q1: 2024年7月 | R1: 2024年8月 | S1: 2024年9月 | T1: 2024年10月 | U1: 2024年11月 | V1: 2024年12月 | W1: 2025年1月 | X1: 2025年2月 | Y1: 2025年3月 | Z1: 2025年4月 | AA1: 2025年5月 | AB1: 2025年6月 | AC1: 2025年7月 | AD1: 2025年8月 | AE1: 2025年9月 | AF1: 2025年10月 | AG1: 2025年11月 | AH1: 2025年12月 | AI1: 2023年使用量(U23) | AJ1: 2024年使用量(U24) | AK1: 2025年使用量(U25) | AL1: 南機廠庫存量 | AM1: 新北捷_請購點 | AN1: 新北捷_庫存單位 | AO1: 交貨期(L) | AP1: 採購前置時間(P) | AQ1: 安全等級 | AR1: 2023請購點(ROP) | AS1: 2024請購點(ROP) | AT1: 2025請購點(ROP)
A2: 93.14.0001.LO | B2: 電動起子馬達碳刷/廠牌：BOSCH，型號：2609199169 | H2: 2 | AI2: =SUM(C2:J2) -> 2 | AJ2: =SUM(K2:V2) -> 0 | AK2: =SUM(W2:AH2) -> 0 | AL2: 0 | AN2: 件 | AP2: 30 | AQ2: 2 | AR2: 1 | AS2: 0 | AT2: 0
A3: 94.01.0002.AF | B3: 油漆筆(白)/白色 | D3: 33 | P3: 10 | AB3: 10 | AI3: =SUM(C3:J3) -> 33 | AJ3: =SUM(K3:V3) -> 10 | AK3: =SUM(W3:AH3) -> 10 | AL3: 990 | AN3: PC | AP3: 30 | AQ3: 3 | AR3: 6 | AS3: 2 | AT3: 2
A4: 94.01.0003.AF | B4: 油漆筆(黃)/黃色 | D4: 18 | AI4: =SUM(C4:J4) -> 18 | AJ4: =SUM(K4:V4) -> 0 | AK4: =SUM(W4:AH4) -> 0 | AL4: 32 | AM4: 1 | AN4: PC | AP4: 30 | AQ4: 3 | AR4: 4 | AS4: 0 | AT4: 0
A5: 94.01.0007.AF | B5: 噴漆(白)/1.顏色: 白色 2.容量:400ml/罐(含)以上/CN | D5: 17 | AI5: =SUM(C5:J5) -> 17 | AJ5: =SUM(K5:V5) -> 0 | AK5: =SUM(W5:AH5) -> 0 | AL5: 57 | AM5: 1 | AN5: CN | AP5: 30 | AQ5: 3 | AR5: 3 | AS5: 0 | AT5: 0
A6: 94.01.0009.AF | B6: 噴漆(黑)/1.顏色: 黑色 2.容量:400ml/罐(含)以上/CN | D6: 8 | AI6: =SUM(C6:J6) -> 8 | AJ6: =SUM(K6:V6) -> 0 | AK6: =SUM(W6:AH6) -> 0 | AL6: 67 | AM6: 1 | AN6: CN | AP6: 30 | AQ6: 3 | AR6: 2 | AS6: 0 | AT6: 0
A7: 94.01.0014.LO | B7: 冷鍍鋅漆/13oz/CN，噴霧式，產品標示之保存期限：自製造日起至少 36 個月 | D7: 5 | U7: 1 | AF7: 2 | AI7: =SUM(C7:J7) -> 5 | AJ7: =SUM(K7:V7) -> 1 | AK7: =SUM(W7:AH7) -> 2 | AL7: 40 | AM7: 0 | AN7: CN | AP7: 30 | AQ7: 2 | AR7: 1 | AS7: 1 | AT7: 1
A8: 94.02.0001.LO | B8: 蒸餾水/1.適用電瓶加水用，不含金屬導電物 2.包裝方式：5GAL/桶 | L8: 5 | P8: 16 | Q8: 5 | V8: 6 | X8: 5 | AB8: 16 | AI8: =SUM(C8:J8) -> 0 | AJ8: =SUM(K8:V8) -> 32 | AK8: =SUM(W8:AH8) -> 21 | AL8: 72 | AM8: 0 | AN8: PL | AP8: 30 | AQ8: 2 | AR8: 0 | AS8: 6 | AT8: 4
A9: 94.03.0006.LO | B9: 木柄銅絲刷/植毛寬度:20mm±3mm，植毛長度:75mm±5mm，毛長:15mm±3mm，總長220mm以上 | D9: 15 | AG9: 20 | AI9: =SUM(C9:J9) -> 15 | AJ9: =SUM(K9:V9) -> 0 | AK9: =SUM(W9:AH9) -> 20 | AL9: 94 | AM9: 0 | AN9: EA | AP9: 30 | AQ9: 2 | AR9: 3 | AS9: 0 | AT9: 4
A10: 94.07.0010.LO | B10: 氬氣/充填壓力120kg/c㎡以上，容積6立方米 | H10: 1 | AI10: =SUM(C10:J10) -> 1 | AJ10: =SUM(K10:V10) -> 0 | AK10: =SUM(W10:AH10) -> 0 | AL10: 0 | AN10: PL | AP10: 30 | AQ10: 2 | AR10: 1 | AS10: 0 | AT10: 0
A11: 94.07.0017.LO | B11: 氮氣(含瓶身)/1.充填壓力：190kg/c㎡以上，水容積：50L，容積：10立方米。 2.適用氣體名稱：氮氣。 3.接頭型式：CGA580。 4.須含鋼瓶身。 | S11: 1 | U11: 1 | V11: 1 | AE11: 1 | AF11: 2 | AH11: 6 | AI11: =SUM(C11:J11) -> 0 | AJ11: =SUM(K11:V11) -> 3 | AK11: =SUM(W11:AH11) -> 9 | AL11: 3 | AM11: 0 | AN11: PL | AP11: 30 | AQ11: 2 | AR11: 0 | AS11: 1 | AT11: 2
A12: 94.12.0001.LO | B12: PVC絕緣膠布(紅色)/紅色 0.2mm*19mm*10m | J12: 2 | O12: 2 | R12: 1 | S12: 2 | AA12: 2 | AD12: 1 | AE12: 2 | AI12: =SUM(C12:J12) -> 2 | AJ12: =SUM(K12:V12) -> 5 | AK12: =SUM(W12:AH12) -> 5 | AL12: 0 | AN12: RL | AP12: 30 | AQ12: 2 | AR12: 1 | AS12: 1 | AT12: 1
A13: 94.12.0002.LO | B13: PVC絕緣膠布(黑色)/黑色 0.2mm*19mm 10m | J13: 2 | O13: 3 | R13: 1 | S13: 5 | AA13: 3 | AD13: 1 | AE13: 5 | AI13: =SUM(C13:J13) -> 2 | AJ13: =SUM(K13:V13) -> 9 | AK13: =SUM(W13:AH13) -> 9 | AL13: 0 | AN13: RL | AP13: 30 | AQ13: 2 | AR13: 1 | AS13: 2 | AT13: 2
A14: 94.12.0003.LO | B14: PVC絕緣膠布(黃色)/黃色 0.2mm*19mm*10m | J14: 1 | O14: 1 | AA14: 1 | AI14: =SUM(C14:J14) -> 1 | AJ14: =SUM(K14:V14) -> 1 | AK14: =SUM(W14:AH14) -> 1 | AL14: 0 | AN14: RL | AP14: 30 | AQ14: 2 | AR14: 1 | AS14: 1 | AT14: 1
A15: 94.12.0004.LO | B15: PVC絕緣膠布(白色)/白色 0.2mm*19mm*10m | J15: 2 | O15: 2 | S15: 2 | AA15: 2 | AE15: 2 | AI15: =SUM(C15:J15) -> 2 | AJ15: =SUM(K15:V15) -> 4 | AK15: =SUM(W15:AH15) -> 4 | AL15: 0 | AN15: RL | AP15: 30 | AQ15: 2 | AR15: 1 | AS15: 1 | AT15: 1
A16: 94.12.0005.LO | B16: PVC絕緣膠布(綠色)/綠色 0.2mm*19mm*10m | J16: 2 | O16: 2 | AA16: 2 | AI16: =SUM(C16:J16) -> 2 | AJ16: =SUM(K16:V16) -> 2 | AK16: =SUM(W16:AH16) -> 2 | AL16: 0 | AN16: RL | AP16: 30 | AQ16: 2 | AR16: 1 | AS16: 1 | AT16: 1
A17: 94.14.0007.LO | B17: 止洩帶/一般管路防漏用，規格：厚度：0.1mm、寬度：13mm、每捲長度：15m以上 | J17: 2 | M17: 5 | R17: 6 | Y17: 5 | AD17: 6 | AF17: 5 | AI17: =SUM(C17:J17) -> 2 | AJ17: =SUM(K17:V17) -> 11 | AK17: =SUM(W17:AH17) -> 16 | AL17: 30 | AM17: 0 | AN17: RL | AP17: 30 | AQ17: 2 | AR17: 1 | AS17: 2 | AT17: 3
A18: 94.14.0008.LO | B18: 矽利康(施敏打硬，黑)/1、廠牌：CEMEDINE ，型號：SUPER X NO.8008，容量:333ml/條，顏色：黑。 2、保存期限：自製造日起至少12個月。 | M18: 1 | Q18: 4 | Y18: 1 | AI18: =SUM(C18:J18) -> 0 | AJ18: =SUM(K18:V18) -> 5 | AK18: =SUM(W18:AH18) -> 1 | AL18: 48 | AM18: 0 | AN18: EA | AP18: 30 | AQ18: 2 | AR18: 0 | AS18: 1 | AT18: 1
A19: 94.14.0009.LO | B19: 熱縮套管(10.4mm)/1、廠牌：KSS，型號：F32-10 。 2、尺寸：收縮前內徑10.4mm±0.4mm。 3、內徑收縮率50%以上。 4、顏色：黑色。 5、包裝：50m/捲。 | R19: 1 | AD19: 1 | AF19: 1 | AI19: =SUM(C19:J19) -> 0 | AJ19: =SUM(K19:V19) -> 1 | AK19: =SUM(W19:AH19) -> 2 | AL19: 4 | AM19: 0 | AN19: RL | AP19: 30 | AQ19: 2 | AR19: 0 | AS19: 1 | AT19: 1
A20: 94.14.0010.LO | B20: 熱縮套管(3.5mm)/1、廠牌：KSS，型號：F32-3。 2、尺寸：收縮前內徑3.5mm±0.3mm。 3、內徑收縮率50%以上。 4、顏色：黑色。 5、包裝：200m/捲。 | R20: 1 | AD20: 1 | AF20: 1 | AI20: =SUM(C20:J20) -> 0 | AJ20: =SUM(K20:V20) -> 1 | AK20: =SUM(W20:AH20) -> 2 | AL20: 4 | AM20: 0 | AN20: RL | AP20: 30 | AQ20: 2 | AR20: 0 | AS20: 1 | AT20: 1
A21: 94.14.0011.LO | B21: PVC絕緣膠布(藍色)/藍色 0.2mm*19mm*10m。 | S21: 2 | AE21: 2 | AI21: =SUM(C21:J21) -> 0 | AJ21: =SUM(K21:V21) -> 2 | AK21: =SUM(W21:AH21) -> 2 | AL21: 0 | AM21: 0 | AN21: EA | AP21: 30 | AQ21: 2 | AR21: 0 | AS21: 1 | AT21: 1
A22: 94.16.0011.LO | B22: 凡士林(潤滑用)/容量:1kg/瓶 | D22: 2 | AI22: =SUM(C22:J22) -> 2 | AJ22: =SUM(K22:V22) -> 0 | AK22: =SUM(W22:AH22) -> 0 | AL22: 15 | AM22: 0 | AN22: CN | AP22: 30 | AQ22: 2 | AR22: 1 | AS22: 0 | AT22: 0
A23: 94.16.0013.LO | B23: 液壓油(SHELL TELLUS S2 MX 46)/1.廠牌：SHELL、型號：TELLUS S2 MX 46。2.包裝方式：209公升/桶。3.產品標示之保存期限：自製造日起至少48 個月。 | E23: 4 | N23: 1 | Q23: 3 | Z23: 1 | AC23: 4 | AI23: =SUM(C23:J23) -> 4 | AJ23: =SUM(K23:V23) -> 4 | AK23: =SUM(W23:AH23) -> 5 | AL23: 1 | AM23: 0 | AN23: PL | AP23: 30 | AQ23: 2 | AR23: 1 | AS23: 1 | AT23: 1
A24: 94.16.0015.LO | B24: 除銹潤滑油/具有滲透除銹、潤滑鎖頭、消除因機械磨擦產生雜聲等功能，可作為各類金屬或一般材質零組件的維修保養使用，包裝方式：380ml以上，產品標示之保存期限：自製造日起至少 24 個月 | D24: 84 | AF24: 5 | AG24: 5 | AH24: 5 | AI24: =SUM(C24:J24) -> 84 | AJ24: =SUM(K24:V24) -> 0 | AK24: =SUM(W24:AH24) -> 15 | AL24: 62 | AM24: 0 | AN24: CN | AP24: 30 | AQ24: 2 | AR24: 15 | AS24: 0 | AT24: 3
A25: 94.17.0001.LO | B25: 扭力標示劑/1.容量:1 o.z 2.用途:用於螺絲、螺帽鎖固後標示使用 3.顏色:螢光粉紅或橘色 4.產品標示之保存期限：自製造日起至少24個月。 | D25: 153 | AI25: =SUM(C25:J25) -> 153 | AJ25: =SUM(K25:V25) -> 0 | AK25: =SUM(W25:AH25) -> 0 | AL25: 39 | AM25: 0 | AN25: EA | AP25: 30 | AQ25: 2 | AR25: 27 | AS25: 0 | AT25: 0
A26: 94.17.0004.LO | B26: 油漆筆(綠色)/(1)廠牌：雪人牌 (2)顏色：綠色 (3)筆頭寬度：1.5~3mm (4)筆頭材質：壓克力 (5)須適用於鐵板、金屬、玻璃、塑膠、紙類、皮革、布類等材質，畫記後經擦拭，不褪色、脫漆 (6)產品標示之保存期限：自製造日起至少30個月 | D26: 12 | AI26: =SUM(C26:J26) -> 12 | AJ26: =SUM(K26:V26) -> 0 | AK26: =SUM(W26:AH26) -> 0 | AL26: 0 | AN26: PC | AP26: 30 | AQ26: 3 | AR26: 3 | AS26: 0 | AT26: 0
A27: 94.18.0003.LO | B27: 防銹潤滑油/1、廠牌：LOCTITE，型號：8023。2、容量：1LB/罐(或16盎司/罐)。3、產品標示之保存期限：自製造日起至少 60 個月。 | F27: 3 | H27: 2 | M27: 2 | O27: 2 | P27: 6 | S27: 4 | T27: 4 | U27: 1 | Y27: 2 | AA27: 2 | AB27: 6 | AE27: 4 | AI27: =SUM(C27:J27) -> 5 | AJ27: =SUM(K27:V27) -> 19 | AK27: =SUM(W27:AH27) -> 14 | AL27: 13 | AM27: 0 | AN27: CN | AP27: 30 | AQ27: 2 | AR27: 1 | AS27: 4 | AT27: 3
A28: 94.18.0007.LO | B28: 螺絲膠243/1、廠牌：LOCTITE。 2、型號：243。 3、包裝方式：50ml/罐。 4、產品標示之保存期限：自製造日起至少18個月。 | P28: 3 | S28: 4 | T28: 4 | U28: 2 | AB28: 3 | AE28: 4 | AF28: 5 | AG28: 5 | AI28: =SUM(C28:J28) -> 0 | AJ28: =SUM(K28:V28) -> 13 | AK28: =SUM(W28:AH28) -> 17 | AL28: 35 | AM28: 0 | AN28: CN | AP28: 30 | AQ28: 2 | AR28: 0 | AS28: 3 | AT28: 3
A29: 94.18.0008.LO | B29: 防卡劑/1、廠牌：LOCTITE。 2、型號：767或LB8150。 3、包裝方式：1LB/罐。 4、產品標示之保存期限：自製造日起至少36個月。 | P29: 2 | T29: 1 | U29: 2 | AB29: 2 | AI29: =SUM(C29:J29) -> 0 | AJ29: =SUM(K29:V29) -> 5 | AK29: =SUM(W29:AH29) -> 2 | AL29: 6 | AM29: 0 | AN29: CN | AP29: 30 | AQ29: 2 | AR29: 0 | AS29: 1 | AT29: 1
A30: 94.20.0003.AF | B30: 警示膠帶/48mmx25M PVC黑黃 | D30: 35 | R30: 1 | AD30: 1 | AI30: =SUM(C30:J30) -> 35 | AJ30: =SUM(K30:V30) -> 1 | AK30: =SUM(W30:AH30) -> 1 | AL30: 4 | AM30: 1 | AN30: CL | AP30: 30 | AQ30: 2 | AR30: 7 | AS30: 1 | AT30: 1
A31: 94.20.0005.AF | B31: 棉紗手套/20兩 | L31: 30 | P31: 20 | R31: 2 | V31: 5 | X31: 30 | AB31: 20 | AD31: 2 | AI31: =SUM(C31:J31) -> 0 | AJ31: =SUM(K31:V31) -> 57 | AK31: =SUM(W31:AH31) -> 52 | AL31: 846 | AM31: 1 | AN31: BL | AP31: 30 | AQ31: 2 | AR31: 0 | AS31: 10 | AT31: 10
A32: 94.22.0003.LO | B32: 瓦楞紙板/厚:3mm以上,長:180cm以上,寬:138cm以上;材質:3層瓦楞紙板 | O32: 10 | AA32: 10 | AI32: =SUM(C32:J32) -> 0 | AJ32: =SUM(K32:V32) -> 10 | AK32: =SUM(W32:AH32) -> 10 | AL32: 383 | AM32: 0 | AN32: EA | AP32: 30 | AQ32: 4 | AR32: 0 | AS32: 2 | AT32: 2
A33: 94.22.0004.LO | B33: 工業用伸縮膜/17ux50cmx500m | R33: 1 | S33: 6 | AD33: 1 | AE33: 6 | AI33: =SUM(C33:J33) -> 0 | AJ33: =SUM(K33:V33) -> 7 | AK33: =SUM(W33:AH33) -> 7 | AL33: 1 | AM33: 0 | AN33: 支 | AP33: 30 | AQ33: 4 | AR33: 0 | AS33: 2 | AT33: 2
A34: 94.22.0005.LO | B34: 夾鏈袋(由任袋)8號/1.市售規格8號 24*17cm 。 2.每包100只入。 | R34: 2 | AD34: 2 | AF34: 1 | AI34: =SUM(C34:J34) -> 0 | AJ34: =SUM(K34:V34) -> 2 | AK34: =SUM(W34:AH34) -> 3 | AL34: 1 | AM34: 0 | AN34: PG | AP34: 30 | AQ34: 4 | AR34: 0 | AS34: 1 | AT34: 1
A35: 94.22.0006.LO | B35: 夾鏈袋(由任袋)6號/1.市售規格6號 12*17cm。 2.每包100只入。 | R35: 2 | AD35: 2 | AI35: =SUM(C35:J35) -> 0 | AJ35: =SUM(K35:V35) -> 2 | AK35: =SUM(W35:AH35) -> 2 | AL35: 2 | AM35: 0 | AN35: PG | AP35: 30 | AQ35: 4 | AR35: 0 | AS35: 1 | AT35: 1
A36: 94.22.0007.LO | B36: 夾鏈袋(由任袋)10號/1.市售規格10號 34*24cm。 2.每包100只入。 | R36: 1 | AD36: 1 | AF36: 1 | AI36: =SUM(C36:J36) -> 0 | AJ36: =SUM(K36:V36) -> 1 | AK36: =SUM(W36:AH36) -> 2 | AL36: 2 | AM36: 0 | AN36: PG | AP36: 30 | AQ36: 4 | AR36: 0 | AS36: 1 | AT36: 1
A37: 94.22.0008.LO | B37: 夾鏈袋(由任袋)12號/1.市售規格12號 34*45cm。 2.每包100只入。 | R37: 1 | AD37: 1 | AI37: =SUM(C37:J37) -> 0 | AJ37: =SUM(K37:V37) -> 1 | AK37: =SUM(W37:AH37) -> 1 | AL37: 2 | AM37: 0 | AN37: PG | AP37: 30 | AQ37: 4 | AR37: 0 | AS37: 1 | AT37: 1
A38: 94.23.0011.AF | B38: 洗手粉/約3.5kg/盒 | E38: 34 | L38: 20 | P38: 10 | U38: 10 | X38: 20 | AB38: 10 | AC38: 15 | AF38: 20 | AH38: 15 | AI38: =SUM(C38:J38) -> 34 | AJ38: =SUM(K38:V38) -> 40 | AK38: =SUM(W38:AH38) -> 80 | AL38: 37 | AM38: 1 | AN38: BX | AP38: 30 | AQ38: 3 | AR38: 6 | AS38: 7 | AT38: 14
A39: 94.23.0026.LO | B39: 太空包沙袋/1.長100cm(±10cm)*寬100cm(±10cm)*高110cm(±10cm) 2.負載重量至少1噸 3.需有4個吊耳以供吊運,內部不需內裹,開口全開 4.材質使用聚丙烯或精對苯二甲酸。 | E39: 10 | F39: 15 | Q39: 21 | AH39: 30 | AI39: =SUM(C39:J39) -> 25 | AJ39: =SUM(K39:V39) -> 21 | AK39: =SUM(W39:AH39) -> 30 | AL39: 3 | AM39: 0 | AN39: EA | AP39: 30 | AQ39: 2 | AR39: 5 | AS39: 4 | AT39: 6
A40: 94.23.0028.LO | B40: 抹布/長：35~55cm，寬：35~55cm，顏色：白色，具吸水性，包裝方式：5kg/包 | D40: 270 | L40: 20 | P40: 43 | R40: 3 | S40: 3 | T40: 3 | U40: 20 | V40: 6 | X40: 20 | AB40: 43 | AC40: 4 | AD40: 3 | AE40: 3 | AF40: 10 | AH40: 23 | AI40: =SUM(C40:J40) -> 270 | AJ40: =SUM(K40:V40) -> 98 | AK40: =SUM(W40:AH40) -> 106 | AL40: 165 | AM40: 0 | AN40: PG | AP40: 30 | AQ40: 3 | AR40: 48 | AS40: 18 | AT40: 19
A41: 94.23.0029.LO | B41: 環保高壓除塵氣/1.無閃點(No flash point nonflammable) 2.完全不破壞臭氧層(O.D.P Value=0) 3.不含水氣(Moisture Free,含水量 25/1000000以下) 4.無殘留物(%Volatile=100) 5.每罐罐裝重量須達10oz或284g以上 | L41: 5 | X41: 5 | AF41: 20 | AI41: =SUM(C41:J41) -> 0 | AJ41: =SUM(K41:V41) -> 5 | AK41: =SUM(W41:AH41) -> 25 | AL41: 168 | AM41: 0 | AN41: CN | AP41: 30 | AQ41: 2 | AR41: 0 | AS41: 1 | AT41: 5
A42: 94.23.0032.LO | B42: 脫脂清潔劑(LOCTITE 7063)/1.廠牌：LOCTITE，型號：7063。 2.容量：400ml/罐。 3.產品標示之保存期限：自製造日起至少 36 個月。 | Q42: 2 | R42: 8 | T42: 15 | U42: 1 | V42: 6 | AD42: 8 | AG42: 5 | AI42: =SUM(C42:J42) -> 0 | AJ42: =SUM(K42:V42) -> 32 | AK42: =SUM(W42:AH42) -> 13 | AL42: 45 | AM42: 0 | AN42: EA | AP42: 30 | AQ42: 2 | AR42: 0 | AS42: 6 | AT42: 3
A43: 94.23.0034.LO | B43: 防護手套(防油用)/1.尺寸：L號。 2.材質：NBR。 3.包裝：100件/盒。 4.無粉。 | Q43: 10 | R43: 3 | S43: 42 | T43: 3 | U43: 23 | V43: 5 | AD43: 3 | AE43: 42 | AF43: 60 | AI43: =SUM(C43:J43) -> 0 | AJ43: =SUM(K43:V43) -> 86 | AK43: =SUM(W43:AH43) -> 105 | AL43: 45 | AM43: 0 | AN43: PG | AP43: 30 | AQ43: 2 | AR43: 0 | AS43: 15 | AT43: 19
A44: 94.26.0011.AF | B44: 平墊片/SUS304 M6 | H44: 400 | AI44: =SUM(C44:J44) -> 400 | AJ44: =SUM(K44:V44) -> 0 | AK44: =SUM(W44:AH44) -> 0 | AL44: 0 | AM44: 1 | AN44: PC | AP44: 30 | AQ44: 2 | AR44: 70 | AS44: 0 | AT44: 0
A45: 94.28.0011.LO | B45: 帶柄砂布輪-80#/1、參考廠牌：Kingdom Abrasive或同等品。 2、規格：50x25x6 mm (外徑*厚*柄徑)、號數：80#。 | P45: 70 | AB45: 70 | AI45: =SUM(C45:J45) -> 0 | AJ45: =SUM(K45:V45) -> 70 | AK45: =SUM(W45:AH45) -> 70 | AL45: 0 | AN45: PC | AP45: 30 | AQ45: 2 | AR45: 0 | AS45: 13 | AT45: 13
A46: 94.30.0001.LO | B46: 煤油/1.化學成份:C10H22至C16H34的混合物。2.包裝：20公升/桶。3.產品標示之保存期限：自製造日起至少36個月。 | J46: 2 | L46: 9 | V46: 24 | X46: 9 | AI46: =SUM(C46:J46) -> 2 | AJ46: =SUM(K46:V46) -> 33 | AK46: =SUM(W46:AH46) -> 9 | AL46: 0 | AN46: PL | AP46: 30 | AQ46: 2 | AR46: 1 | AS46: 6 | AT46: 2
A47: 94.31.0010.LO | B47: 接點復活劑/1.不含氟氯碳化物。 2.速乾無漬。 3.比重(20℃~25℃):0.67~1.56。 4.Kauri-BTanol Value:26~41kb。 5.表面張力(25℃):17~19dynes/cm或(20℃):21dynes/cm。 6.包裝350g以上。 7.適用機悈設備及電氣用品。 8.產品標示之保存期限：自製造日起至少 12 個月。 | Q47: 1 | AF47: 2 | AH47: 3 | AI47: =SUM(C47:J47) -> 0 | AJ47: =SUM(K47:V47) -> 1 | AK47: =SUM(W47:AH47) -> 5 | AL47: 10 | AM47: 0 | AN47: EA | AP47: 30 | AQ47: 2 | AR47: 0 | AS47: 1 | AT47: 1
A48: 94.99.0001.LO | B48: 液狀瞬間膠(10g)/液狀瞬間膠，10g包裝 | Q48: 3 | AI48: =SUM(C48:J48) -> 0 | AJ48: =SUM(K48:V48) -> 3 | AK48: =SUM(W48:AH48) -> 0 | AL48: 1 | AM48: 0 | AN48: EA | AP48: 30 | AQ48: 2 | AR48: 0 | AS48: 1 | AT48: 0
A49: 94.99.0002.LO | B49: 高耐久無鉛苯防鏽噴漆(透明)/高耐久無鉛苯防鏽噴漆(透明) 300ML | D49: 15 | AI49: =SUM(C49:J49) -> 15 | AJ49: =SUM(K49:V49) -> 0 | AK49: =SUM(W49:AH49) -> 0 | AL49: 1 | AM49: 0 | AN49: CN | AP49: 30 | AQ49: 2 | AR49: 3 | AS49: 0 | AT49: 0
A50: 94.99.0004.LO | B50: 尼龍刷木柄-20cm/尼龍刷木柄-20cm | D50: 17 | AI50: =SUM(C50:J50) -> 17 | AJ50: =SUM(K50:V50) -> 0 | AK50: =SUM(W50:AH50) -> 0 | AL50: 2 | AM50: 0 | AN50: EA | AP50: 30 | AQ50: 3 | AR50: 3 | AS50: 0 | AT50: 0
A51: 94.99.0009.LO | B51: 木柄鋼刷帶刮刀/木柄鋼刷帶刮刀 | D51: 17 | AI51: =SUM(C51:J51) -> 17 | AJ51: =SUM(K51:V51) -> 0 | AK51: =SUM(W51:AH51) -> 0 | AL51: 7 | AM51: 0 | AN51: EA | AP51: 30 | AQ51: 2 | AR51: 3 | AS51: 0 | AT51: 0
A52: 94.99.0010.LO | B52: 遮蔽紙膠帶/ 遮蔽紙膠帶 1" | R52: 1 | U52: 3 | AD52: 1 | AF52: 11 | AI52: =SUM(C52:J52) -> 0 | AJ52: =SUM(K52:V52) -> 4 | AK52: =SUM(W52:AH52) -> 12 | AL52: 40 | AM52: 0 | AN52: EA | AP52: 30 | AQ52: 3 | AR52: 0 | AS52: 1 | AT52: 3
A53: 94.99.0011.LO | B53: 遮蔽膠帶/遮蔽膠帶(1R)14mm*35公尺 | Q53: 5 | R53: 1 | T53: 2 | U53: 8 | AD53: 1 | AF53: 10 | AI53: =SUM(C53:J53) -> 0 | AJ53: =SUM(K53:V53) -> 16 | AK53: =SUM(W53:AH53) -> 11 | AL53: 51 | AM53: 0 | AN53: EA | AP53: 30 | AQ53: 3 | AR53: 0 | AS53: 3 | AT53: 2
A54: 94.99.0013.LO | B54: 專業多功能中性矽利康(淺灰)/專業多功能中性矽利康(淺灰)354g | D54: 29 | AC54: 37 | AF54: 19 | AI54: =SUM(C54:J54) -> 29 | AJ54: =SUM(K54:V54) -> 0 | AK54: =SUM(W54:AH54) -> 56 | AL54: 53 | AM54: 0 | AN54: EA | AP54: 30 | AQ54: 2 | AR54: 6 | AS54: 0 | AT54: 10
A55: 94.99.0016.LO | B55: 噴霧式黃油/恐龍192噴霧式黃油 420ml 產品標示之保存期限：自製造日起至少 36 個月 | D55: 22 | AF55: 5 | AI55: =SUM(C55:J55) -> 22 | AJ55: =SUM(K55:V55) -> 0 | AK55: =SUM(W55:AH55) -> 5 | AL55: 143 | AM55: 0 | AN55: BT | AP55: 30 | AQ55: 2 | AR55: 4 | AS55: 0 | AT55: 1
A56: 94.99.0018.LO | B56: 3吋海力士刷/3吋海力士刷 | D56: 7 | AI56: =SUM(C56:J56) -> 7 | AJ56: =SUM(K56:V56) -> 0 | AK56: =SUM(W56:AH56) -> 0 | AL56: 8 | AM56: 0 | AN56: EA | AP56: 30 | AQ56: 3 | AR56: 2 | AS56: 0 | AT56: 0
A57: 94.99.0019.LO | B57: 可調式彎頭豬鬃刷4吋/可調式彎頭豬鬃刷4吋 | D57: 14 | AI57: =SUM(C57:J57) -> 14 | AJ57: =SUM(K57:V57) -> 0 | AK57: =SUM(W57:AH57) -> 0 | AL57: 4 | AM57: 0 | AN57: EA | AP57: 30 | AQ57: 3 | AR57: 3 | AS57: 0 | AT57: 0
A58: 94.99.0020.LO | B58: 特級羊毛刷2吋/特級羊毛刷2吋 | D58: 8 | AI58: =SUM(C58:J58) -> 8 | AJ58: =SUM(K58:V58) -> 0 | AK58: =SUM(W58:AH58) -> 0 | AL58: 29 | AM58: 0 | AN58: EA | AP58: 30 | AQ58: 3 | AR58: 2 | AS58: 0 | AT58: 0
A59: 94.99.0023.LO | B59: 專業多功能中性矽利康(黑色)/專業多功能中性矽利康(黑色)354g | D59: 10 | AI59: =SUM(C59:J59) -> 10 | AJ59: =SUM(K59:V59) -> 0 | AK59: =SUM(W59:AH59) -> 0 | AL59: 3 | AM59: 0 | AN59: EA | AP59: 30 | AQ59: 2 | AR59: 2 | AS59: 0 | AT59: 0
A60: 94.99.0024.LO | B60: 天然除膠去污劑/天然除膠去污劑473ML | D60: 32 | P60: 10 | Q60: 6 | R60: 5 | S60: 10 | U60: 11 | V60: 5 | AB60: 10 | AD60: 5 | AE60: 10 | AF60: 30 | AG60: 6 | AI60: =SUM(C60:J60) -> 32 | AJ60: =SUM(K60:V60) -> 47 | AK60: =SUM(W60:AH60) -> 61 | AL60: 28 | AM60: 0 | AN60: CN | AP60: 30 | AQ60: 3 | AR60: 6 | AS60: 9 | AT60: 11
A61: 94.99.0025.LO | B61: 乾式潤滑劑(含PTFE)/乾式潤滑劑(含PTFE) 360ML | D61: 205 | AC61: 11 | AF61: 25 | AG61: 26 | AI61: =SUM(C61:J61) -> 205 | AJ61: =SUM(K61:V61) -> 0 | AK61: =SUM(W61:AH61) -> 62 | AL61: 2 | AM61: 0 | AN61: CN | AP61: 30 | AQ61: 2 | AR61: 36 | AS61: 0 | AT61: 11
A62: 94.99.0026.LO | B62: 實用型豬鬃刷2吋/實用型豬鬃刷2吋 | D62: 15 | AI62: =SUM(C62:J62) -> 15 | AJ62: =SUM(K62:V62) -> 0 | AK62: =SUM(W62:AH62) -> 0 | AL62: 8 | AM62: 0 | AN62: EA | AP62: 30 | AQ62: 3 | AR62: 3 | AS62: 0 | AT62: 0
A63: 94.99.0027.LO | B63: 雙面泡棉膠帶/雙面泡棉膠帶18mmx5M | D63: 29 | AI63: =SUM(C63:J63) -> 29 | AJ63: =SUM(K63:V63) -> 0 | AK63: =SUM(W63:AH63) -> 0 | AL63: 4 | AM63: 0 | AN63: EA | AP63: 30 | AQ63: 3 | AR63: 6 | AS63: 0 | AT63: 0
A64: 94.99.0028.LO | B64: 束線帶(L800mm*W8.8mm)/束線帶(L800mm*W8.8mm)公差5%，顏色：白色，包裝方式100PCS/包,承受力>=80kg | D64: 9 | AF64: 2 | AI64: =SUM(C64:J64) -> 9 | AJ64: =SUM(K64:V64) -> 0 | AK64: =SUM(W64:AH64) -> 2 | AL64: 29 | AM64: 0 | AN64: PG | AP64: 30 | AQ64: 2 | AR64: 2 | AS64: 0 | AT64: 1
A65: 94.99.0029.LO | B65: 束線帶(L370mm*W7.6mm)/束線帶(L370mm*W7.6mm)公差5%，顏色：白色，包裝方式100PCS/包,承受力>=54kg | D65: 14 | AF65: 5 | AI65: =SUM(C65:J65) -> 14 | AJ65: =SUM(K65:V65) -> 0 | AK65: =SUM(W65:AH65) -> 5 | AL65: 26 | AM65: 0 | AN65: PG | AP65: 30 | AQ65: 2 | AR65: 3 | AS65: 0 | AT65: 1
A66: 94.99.0030.LO | B66: 束線帶(L150mm*W3.6mm)/束線帶(L150mm*W3.6mm)公差5%，顏色：白色，包裝方式100PCS/包,承受力>=18kg | D66: 45 | AF66: 2 | AI66: =SUM(C66:J66) -> 45 | AJ66: =SUM(K66:V66) -> 0 | AK66: =SUM(W66:AH66) -> 2 | AL66: 15 | AM66: 0 | AN66: PG | AP66: 30 | AQ66: 2 | AR66: 8 | AS66: 0 | AT66: 1
A67: 94.XX.0027.LO | B67: 乾溼兩用吸塵器/1、廠牌：REXON 力山。2、型號：DW20A。3、集屑桶容量：20L。4、工作電壓：110V | N67: 1 | Z67: 1 | AI67: =SUM(C67:J67) -> 0 | AJ67: =SUM(K67:V67) -> 1 | AK67: =SUM(W67:AH67) -> 1 | AL67: 0 | AN67: EA | AP67: 30 | AQ67: 3 | AR67: 0 | AS67: 1 | AT67: 1
A68: 94.XX.0033.LO | B68: 組合式底座3D列印樣品/1、尺寸：孔徑35±1mm，底部外徑80±3mm，高度70±3mm。 2、底部固定板：參考下方附圖。 3、材質：PLA。 | O68: 1 | AA68: 1 | AI68: =SUM(C68:J68) -> 0 | AJ68: =SUM(K68:V68) -> 1 | AK68: =SUM(W68:AH68) -> 1 | AL68: 0 | AN68: EA | AP68: 30 | AQ68: 2 | AR68: 0 | AS68: 1 | AT68: 1
A69: 94.XX.0034.LO | B69: 伸縮反射鏡(附燈)/長80+5mm，寬50+5mm，伸縮長度700mm以上，含萬向旋轉頭及LED燈 | O69: 10 | AA69: 10 | AI69: =SUM(C69:J69) -> 0 | AJ69: =SUM(K69:V69) -> 10 | AK69: =SUM(W69:AH69) -> 10 | AL69: 0 | AN69: EA | AP69: 30 | AQ69: 2 | AR69: 0 | AS69: 2 | AT69: 2
A70: 95.32.0004.LO | B70: 鋼瓶手推車/1.推車站立高度105cm。 2.底板尺寸長度24cm、寬度30cm。 3.兩側輪胎：材質為免充氣橡膠輪胎(硬質)，尺寸直徑:15cm、寬度:5cm。 4.後方輪胎：材質為免充氣橡膠輪胎(硬質)，尺寸直徑:10cm、寬度:3cm。 5.須配有鋼瓶固定鎖鐵鍊及煞車止擋裝置。 6.表面須電鍍。 | E70: 1 | AI70: =SUM(C70:J70) -> 1 | AJ70: =SUM(K70:V70) -> 0 | AK70: =SUM(W70:AH70) -> 0 | AL70: 0 | AN70: EA | AP70: 30 | AQ70: 2 | AR70: 1 | AS70: 0 | AT70: 0
A71: 94.18.0009.LO | B71: 螺絲固定劑 592/1、廠牌：LOCTITE。 2、型號：592。 3、包裝方式：250ml/條。 4、產品標示之保存期限：自製造日起至少24 個月。 | T71: 1 | AI71: =SUM(C71:J71) -> 0 | AJ71: =SUM(K71:V71) -> 1 | AK71: =SUM(W71:AH71) -> 0 | AL71: 28 | AM71: 0 | AN71: EA | AP71: 30 | AQ71: 2 | AR71: 0 | AS71: 1 | AT71: 0
A72: 94.32.0043.LO | B72: 鋁管矽利康槍/1.產品材質：高強度鋁合金。 2.適用容量：600ml蠟腸包。 3.適用於袋裝填縫黏著劑。 | AC72: 6 | AI72: =SUM(C72:J72) -> 0 | AJ72: =SUM(K72:V72) -> 0 | AK72: =SUM(W72:AH72) -> 6 | AL72: 0 | AN72: PC | AP72: 30 | AQ72: 2 | AR72: 0 | AS72: 0 | AT72: 2
A73: 94.99.0012.LO | B73: 中性矽利康(透明)/一、專業多功能中性矽利康(透明)300ml。二、產品標示之保存期限：自製造日起至少12個月。三、報廢不需繳回 | AC73: 13 | AI73: =SUM(C73:J73) -> 0 | AJ73: =SUM(K73:V73) -> 0 | AK73: =SUM(W73:AH73) -> 13 | AL73: 3 | AM73: 0 | AN73: EA | AP73: 30 | AQ73: 2 | AR73: 0 | AS73: 0 | AT73: 3
A74: 95.42.0005.LO | B74: 矽利康槍/適用300ml管裝矽利康 | AC74: 6 | AI74: =SUM(C74:J74) -> 0 | AJ74: =SUM(K74:V74) -> 0 | AK74: =SUM(W74:AH74) -> 6 | AL74: 0 | AM74: 0 | AN74: PC | AP74: 30 | AQ74: 2 | AR74: 0 | AS74: 0 | AT74: 2
A75: 94.14.0012.LO | B75: 自熔接修補帶-灰/魔力自熔接修補帶-灰2.54x305cm。報廢不需繳回 | AF75: 2 | AI75: =SUM(C75:J75) -> 0 | AJ75: =SUM(K75:V75) -> 0 | AK75: =SUM(W75:AH75) -> 2 | AL75: 22 | AM75: 0 | AN75: EA | AP75: 30 | AQ75: 2 | AR75: 0 | AS75: 0 | AT75: 1
A76: 94.99.0037.LO | B76: 拉帽M8*26.5/規格：M8X1.25X26.5，A2-70。 | AF76: 100 | AI76: =SUM(C76:J76) -> 0 | AJ76: =SUM(K76:V76) -> 0 | AK76: =SUM(W76:AH76) -> 100 | AL76: 0 | AN76: EA | AP76: 30 | AQ76: 2 | AR76: 0 | AS76: 0 | AT76: 18
A77: 94.99.0032.LO | B77: 防脫落六角螺絲M10/規格：M10X1.5X20，半牙，牙長15mm，A2-70。 | AF77: 100 | AI77: =SUM(C77:J77) -> 0 | AJ77: =SUM(K77:V77) -> 0 | AK77: =SUM(W77:AH77) -> 100 | AL77: 0 | AN77: EA | AP77: 30 | AQ77: 2 | AR77: 0 | AS77: 0 | AT77: 18
A78: 94.99.0035.LO | B78: 六角螺帽M8/規格：M8X1.25，A2-70。 | AF78: 100 | AI78: =SUM(C78:J78) -> 0 | AJ78: =SUM(K78:V78) -> 0 | AK78: =SUM(W78:AH78) -> 100 | AL78: 0 | AM78: 0 | AN78: EA | AP78: 30 | AQ78: 2 | AR78: 0 | AS78: 0 | AT78: 18
A79: 94.23.0046.LO | B79: 除膠劑(84391)/1、廠牌：3M。2、型號：M-84391。3、容量：265g/罐。 | AF79: 1 | AI79: =SUM(C79:J79) -> 0 | AJ79: =SUM(K79:V79) -> 0 | AK79: =SUM(W79:AH79) -> 1 | AL79: 0 | AN79: CN | AP79: 30 | AQ79: 3 | AR79: 0 | AS79: 0 | AT79: 1
A80: 94.23.0047.LO | B80: 多功能除膠去蠟水(8984)/1、廠牌：3M。2、型號：M-8984。3、容量：946ml/罐。 | AF80: 1 | AI80: =SUM(C80:J80) -> 0 | AJ80: =SUM(K80:V80) -> 0 | AK80: =SUM(W80:AH80) -> 1 | AL80: 0 | AN80: CN | AP80: 30 | AQ80: 3 | AR80: 0 | AS80: 0 | AT80: 1
A81: 94.32.0042.LO | B81: M8不銹鋼彈簧墊片/M8不銹鋼彈簧墊片，數量:200入。 | AF81: 2 | AI81: =SUM(C81:J81) -> 0 | AJ81: =SUM(K81:V81) -> 0 | AK81: =SUM(W81:AH81) -> 2 | AL81: 0 | AM81: 0 | AN81: PG | AP81: 30 | AQ81: 2 | AR81: 0 | AS81: 0 | AT81: 1
A82: 94.32.0041.LO | B82: M8不銹鋼平墊片/M8不銹鋼平墊片，數量:200入。 | AF82: 1 | AI82: =SUM(C82:J82) -> 0 | AJ82: =SUM(K82:V82) -> 0 | AK82: =SUM(W82:AH82) -> 1 | AL82: 0 | AM82: 0 | AN82: PG | AP82: 30 | AQ82: 2 | AR82: 0 | AS82: 0 | AT82: 1
A83: 94.99.0034.LO | B83: 防脫落六角螺絲M8/規格：M8X1.25X20，半牙，牙長10mm，A2-70。 | AF83: 200 | AI83: =SUM(C83:J83) -> 0 | AJ83: =SUM(K83:V83) -> 0 | AK83: =SUM(W83:AH83) -> 200 | AL83: 0 | AM83: 0 | AN83: EA | AP83: 30 | AQ83: 2 | AR83: 0 | AS83: 0 | AT83: 35
A84: 94.02.0012.LO | B84: LR44鈕扣電池/LR44鈕扣電池 | AF84: 12 | AI84: =SUM(C84:J84) -> 0 | AJ84: =SUM(K84:V84) -> 0 | AK84: =SUM(W84:AH84) -> 12 | AL84: 0 | AN84: EA | AP84: 30 | AQ84: 2 | AR84: 0 | AS84: 0 | AT84: 3
A85: 94.32.0003.AF | B85: PVC絕緣膠布(白色)/白色 0.2mm*19mm*10m，報廢不需繳回 | AF85: 2 | AI85: =SUM(C85:J85) -> 0 | AJ85: =SUM(K85:V85) -> 0 | AK85: =SUM(W85:AH85) -> 2 | AL85: 15 | AM85: 0 | AN85: RL | AP85: 30 | AQ85: 2 | AR85: 0 | AS85: 0 | AT85: 1
A86: 94.32.0001.AF | B86: PVC絕緣膠布(黑色)/黑色 0.2mm*19mm*10m，報廢不需繳回。 | AF86: 2 | AI86: =SUM(C86:J86) -> 0 | AJ86: =SUM(K86:V86) -> 0 | AK86: =SUM(W86:AH86) -> 2 | AL86: 33 | AM86: 1 | AN86: RL | AP86: 30 | AQ86: 2 | AR86: 0 | AS86: 0 | AT86: 1
A87: 94.02.0007.EV | B87: 3號電池/碳鋅電池，報廢不需繳回 | AF87: 12 | AI87: =SUM(C87:J87) -> 0 | AJ87: =SUM(K87:V87) -> 0 | AK87: =SUM(W87:AH87) -> 12 | AL87: 0 | AM87: 0 | AN87: PCS | AP87: 30 | AQ87: 2 | AR87: 0 | AS87: 0 | AT87: 3
A88: 94.32.0004.AF | B88: PVC絕緣膠布(綠色)/綠色 0.2mm*19mm*10m，報廢不需繳回 | AF88: 2 | AI88: =SUM(C88:J88) -> 0 | AJ88: =SUM(K88:V88) -> 0 | AK88: =SUM(W88:AH88) -> 2 | AL88: 13 | AM88: 1 | AN88: RL | AP88: 30 | AQ88: 2 | AR88: 0 | AS88: 0 | AT88: 1
A89: 94.18.0017.LO | B89: 膏狀瞬間膠(2g)/1、廠牌：3M(或同等品)，型號：6886。 2、包裝：2g，膏狀。 3、保存期限：自製造日起至少12個月。 | AF89: 2 | AI89: =SUM(C89:J89) -> 0 | AJ89: =SUM(K89:V89) -> 0 | AK89: =SUM(W89:AH89) -> 2 | AL89: 10 | AM89: 0 | AN89: EA | AP89: 30 | AQ89: 2 | AR89: 0 | AS89: 0 | AT89: 1
A90: 94.18.0018.LO | B90: 萬能噴膠/1、廠牌：手牌。2、容量：340g/罐。 | AF90: 1 | AI90: =SUM(C90:J90) -> 0 | AJ90: =SUM(K90:V90) -> 0 | AK90: =SUM(W90:AH90) -> 1 | AL90: 0 | AN90: CN | AP90: 30 | AQ90: 3 | AR90: 0 | AS90: 0 | AT90: 1
A91: 94.14.0014.LO | B91: PVC絕緣膠布(黃色)/黃色 0.2mm*19mm*10m。報廢不需繳回 | AF91: 2 | AI91: =SUM(C91:J91) -> 0 | AJ91: =SUM(K91:V91) -> 0 | AK91: =SUM(W91:AH91) -> 2 | AL91: 12 | AM91: 0 | AN91: EA | AP91: 30 | AQ91: 2 | AR91: 0 | AS91: 0 | AT91: 1
A92: 94.99.0031.LO | B92: 內六角沉頭螺絲M8X16/規格：M8X1.25X16，A2-70。 | AF92: 100 | AI92: =SUM(C92:J92) -> 0 | AJ92: =SUM(K92:V92) -> 0 | AK92: =SUM(W92:AH92) -> 100 | AL92: 0 | AM92: 0 | AN92: EA | AP92: 30 | AQ92: 2 | AR92: 0 | AS92: 0 | AT92: 18
A93: 94.32.0030.LO | B93: 安全鋼絲(0.8mm)/1.中硬絲。 2.直徑:0.8mm。 3.重量:1公斤/捲。 | AF93: 1 | AI93: =SUM(C93:J93) -> 0 | AJ93: =SUM(K93:V93) -> 0 | AK93: =SUM(W93:AH93) -> 1 | AL93: 5 | AM93: 0 | AN93: RL | AP93: 30 | AQ93: 2 | AR93: 0 | AS93: 0 | AT93: 1
A94: 94.02.0004.LO | B94: 9號電池/9號一般電池，碳鋅，9V。報廢不需繳回 | AF94: 24 | AI94: =SUM(C94:J94) -> 0 | AJ94: =SUM(K94:V94) -> 0 | AK94: =SUM(W94:AH94) -> 24 | AL94: 4 | AM94: 0 | AN94: EA | AP94: 30 | AQ94: 2 | AR94: 0 | AS94: 0 | AT94: 5
A95: 94.32.0002.AF | B95: PVC絕緣膠布(紅色)/紅色 0.2mm*19mm*10m，報廢不需繳回 | AF95: 2 | AI95: =SUM(C95:J95) -> 0 | AJ95: =SUM(K95:V95) -> 0 | AK95: =SUM(W95:AH95) -> 2 | AL95: 33 | AM95: 1 | AN95: RL | AP95: 30 | AQ95: 2 | AR95: 0 | AS95: 0 | AT95: 1
A96: 94.99.0036.LO | B96: 防水填縫噴劑(透明)/廠牌：FLEX SEAL(或同等品)，容量：17 oz.(482ml)，顏色：透明。 | AF96: 2 | AI96: =SUM(C96:J96) -> 0 | AJ96: =SUM(K96:V96) -> 0 | AK96: =SUM(W96:AH96) -> 2 | AL96: 10 | AM96: 0 | AN96: EA | AP96: 30 | AQ96: 2 | AR96: 0 | AS96: 0 | AT96: 1
A97: 94.99.0038.LO | B97: 矽利康(Glass & Metal)/1、廠牌：DOWSIL(或同等品)，型號：Glass & Metal，容量:300ml/條，顏色：白。 2、保存期限：自製造日起至少12個月。 | AF97: 10 | AI97: =SUM(C97:J97) -> 0 | AJ97: =SUM(K97:V97) -> 0 | AK97: =SUM(W97:AH97) -> 10 | AL97: 0 | AM97: 0 | AN97: EA | AP97: 30 | AQ97: 2 | AR97: 0 | AS97: 0 | AT97: 2
A98: 94.11.0003.LO | B98: 酒精95%/1.產品種類:酒精類乙醇(ETHANOL)2.酒精濃度:未變性酒精95度3.容量:500ml/罐4.包裝方式:12罐/箱或24罐/箱5.罐裝須標示製造日期或出廠日期，報廢不需繳回 | AF98: 10 | AI98: =SUM(C98:J98) -> 0 | AJ98: =SUM(K98:V98) -> 0 | AK98: =SUM(W98:AH98) -> 10 | AL98: 29 | AM98: 0 | AN98: CN | AP98: 30 | AQ98: 3 | AR98: 0 | AS98: 0 | AT98: 2
A99: 94.99.0033.LO | B99: 矽利康(817)/1、廠牌：DOWSIL(或同等品)，型號：817，容量:310ml/條，顏色：白。 2、保存期限：自製造日起至少12個月。 | AF99: 12 | AI99: =SUM(C99:J99) -> 0 | AJ99: =SUM(K99:V99) -> 0 | AK99: =SUM(W99:AH99) -> 12 | AL99: 0 | AM99: 0 | AN99: EA | AP99: 30 | AQ99: 2 | AR99: 0 | AS99: 0 | AT99: 3
A100: 94.02.0006.EV | B100: 4號電池/碳鋅電池，報廢不需繳回 | AF100: 12 | AI100: =SUM(C100:J100) -> 0 | AJ100: =SUM(K100:V100) -> 0 | AK100: =SUM(W100:AH100) -> 12 | AL100: 0 | AM100: 0 | AN100: PCS | AP100: 30 | AQ100: 2 | AR100: 0 | AS100: 0 | AT100: 3
...

Sheet 所有料件
A1: 屬性 | B1: 料號 | C1: 品名 | D1: 品級 | E1: 規格 | F1: 單位 | G1: 倉庫 | H1: 儲位 | I1: 庫存量 | J1: 保存日期
A2: 不可修件 | B2: YA.II.0041.LO | C2: 風扇軸承 | D2: X 工程廠商依契約提供之備品 | E2: 廠牌:ASAHI 型號:UCP 207 | F2: EA | G2: 環狀線南機廠主倉庫 | H2: YSC.02.16.E.01 | I2: 10
A3: 不可修件 | B3: 50.KL.0001.AI | C3: 車廂地板 | D3: X 工程廠商依契約提供之備品 | E3: 1025 x 1470 x 17 mm | F3: PC | G3: 淡海輕軌分存站 | H3: DTS0009 | I3: 2
A4: 不可修件 | B4: 39.26.0006.CC | C4: 亂流調整板 | D4: X 工程廠商依契約提供之備品 | E4: 噴漆室適用 | F4: PC | G4: 淡海輕軌中心倉庫 | H4: DMW1132 | I4: 1
A5: 時限品 | B5: Y4.33.0011.LO | C5: 濕式螢光磁粉液 | D5: X 工程廠商依契約提供之備品 | E5: 廠牌：MAGNAFLUX，型號：14AM，包裝方式：300公克/罐，產品標示之保存期限：自製造日起至少60個月。 | F5: CN | G5: 環狀線南機廠特殊品倉庫 | H5: YSK.03.01.B.01.09.T | I5: 0 | J5: 2025/02/28
A6: 代管捷運局之工具/儀器 | B6: 96.11.0030.KL | C6: 鋼尺(300mm) | D6: X 工程廠商依契約提供之備品 | E6: 300mm | F6: ST | G6: 淡海輕軌電子零件倉 | H6: DE0211 | I6: 0
A7: 代管捷運局之工具/儀器 | B7: 96.11.0030.KL | C7: 鋼尺(300mm) | D7: X 工程廠商依契約提供之備品 | E7: 300mm | F7: ST | G7: 淡海輕軌電子零件倉 | H7: DME0213 | I7: 1
A8: 代管捷運局之工具/儀器 | B8: 96.11.0030.KL | C8: 鋼尺(300mm) | D8: X 工程廠商依契約提供之備品 | E8: 300mm | F8: ST | G8: 淡海輕軌電子零件倉 | H8: DME0211 | I8: 0
A9: 代管捷運局之工具/儀器 | B9: 96.11.0030.KL | C9: 鋼尺(300mm) | D9: X 工程廠商依契約提供之備品 | E9: 300mm | F9: ST | G9: 安坑輕軌電子零件倉 | H9: AME0104 | I9: 0
A10: 代管捷運局之工具/儀器 | B10: 96.11.0030.KL | C10: 鋼尺(300mm) | D10: X 工程廠商依契約提供之備品 | E10: 300mm | F10: ST | G10: 安坑輕軌中心倉庫 | H10: AMW4218 | I10: 0
A11: 代管捷運局之工具/儀器 | B11: 96.11.0030.KL | C11: 鋼尺(300mm) | D11: X 工程廠商依契約提供之備品 | E11: 300mm | F11: ST | G11: 安坑輕軌分存站 | H11: ATS0001 | I11: 0
A12: 代管捷運局之工具/儀器 | B12: 96.11.0030.KL | C12: 鋼尺(300mm) | D12: X 工程廠商依契約提供之備品 | E12: 300mm | F12: ST | G12: 安坑輕軌危險物品倉庫 | H12: AHS0000 | I12: 0
A13: 不可修件 | B13: Y2.PD.0202.LO | C13: JET I UV 貼膜玻璃彩繪(C2-7) | D13: X 工程廠商依契約提供之備品 | E13: 廠牌：艾瓦奇有限公司 規格：101.4cm*83.2cm 說明:板橋站月台滑門-C2-7 | F13: PC | G13: 環狀線南機廠空調倉庫 | H13: YSAC1.08.03.C | I13: 3
A14: 不可修件 | B14: 39.27.0002.CS | C14: 高壓水封組 | D14: X 工程廠商依契約提供之備品 | E14: 高壓清洗泵適用 | F14: PC | G14: 淡海輕軌中心倉庫 | H14: DMW1321 | I14: 1
A15: 不可修件 | B15: Y2.PD.0003.FA | C15: 驅動螺桿總成 | D15: X 工程廠商依契約提供之備品 | E15: 1.廠牌:Faiveley Transport，型號:Z104217-0101。 2.驅動螺桿是驅動機構組件之一部分，螺桿一半長度為右旋螺紋，另一半為左旋螺紋。 3.其功能為帶動自動滑門門扇進行開關門，使用於環狀線Faiveley月臺門系統。 | F15: EA | G15: 環狀線南機廠大型物料倉庫 | H15: YSD.G.01 | I15: 5
A16: 不可修件 | B16: Y1.EE.0022.AS | C16: 電路板(SSRB2) | D16: X 工程廠商依契約提供之備品 | E16: 廠牌:Ansaldo STS或廠牌:Hitachi Rail STS，型號：TA5A.0100001 | F16: EA | G16: 環狀線南機廠空調倉庫 | H16: YSAC1.02.04.C | I16: 1
A17: 不可修件 | B17: Y1.AA.0009.HI | C17: 局部控制單元機架1(LCU) | D17: X 工程廠商依契約提供之備品 | E17: 廠牌：HRI，型號：008974TE03 | F17: EA | G17: 環狀線南機廠主倉庫 | H17: YSC.03.11.B.01 | I17: 2
... A113: 不可修件 | B113: 39.29.0029.GM | C113: 保險絲 7,5 A | D113: X 工程廠商依契約提供之備品 | E113: 電氣系統適用 | F113: PC | G113: 安坑輕軌中心倉庫 | H113: AMW1422 | I113: 10
A114: 時限品 | B114: YA.HH.0012.LO | C114: 皮帶(SPZ-1800) | D114: X 工程廠商依契約提供之備品 | E114: 廠牌:科祿格規格:SPZ-1800 | F114: EA | G114: 環狀線南機廠主倉庫 | H114: YSC.03.09.A.03.11.T | I114: 0 | J114: 2024/01/10
A115: 不可修件 | B115: Y2.PD.0209.LO | C115: 3M長期UV全透明彩繪PVC-月台滑門(右) | D115: N 採購品 | E115: 廠牌：爵士影像事業有限公司 規格：103cm*208cm 說明:月台滑門(右) | F115: PC | G115: 環狀線南機廠大型物料倉庫 | H115: YSD.G | I115: 0
A116: 不可修件 | B116: Y2.PD.0209.LO | C116: 3M長期UV全透明彩繪PVC-月台滑門(右) | D116: N 採購品 | E116: 廠牌：爵士影像事業有限公司 規格：103cm*208cm 說明:月台滑門(右) | F116: PC | G116: 環狀線南機廠空調倉庫 | H116: YSAC1.08.03.D | I116: 0
A117: 不可修件 | B117: Y2.PD.0209.LO | C117: 3M長期UV全透明彩繪PVC-月台滑門(右) | D117: X 工程廠商依契約提供之備品 | E117: 廠牌：爵士影像事業有限公司 規格：103cm*208cm 說明:月台滑門(右) | F117: PC | G117: 環狀線南機廠空調倉庫 | H117: YSAC1.08.03.D | I117: 0
A118: 工具/儀器 | B118: 95.01.0108.KT | C118: 14x18更換式扭力扳手接頭 (開口型) | D118: N 採購品 | E118: 品牌型號KING TONY 34501226M 規格： 1.長度：69mm(±20mm) 2.扭力範圍：359(牛頓-米) | F118: PC | G118: 淡海輕軌中心倉庫 | H118: DMS8888 | I118: 3
A119: 不可修件 | B119: 39.17.0024.TP | C119: 安全切換開關 | D119: X 工程廠商依契約提供之備品 | E119: 電控適用 | F119: PC | G119: 淡海輕軌中心倉庫 | H119: DMW1321 | I119: 1
A120: 不可修件 | B120: 39.17.0024.TP | C120: 安全切換開關 | D120: X 工程廠商依契約提供之備品 | E120: 電控適用 | F120: PC | G120: 安坑輕軌中心倉庫 | H120: AMW1721 | I120: 1
A121: 不可修件 | B121: Y8.BA.0004.OT | C121: 後乘場門門板(無機房1000kg) | D121: X 工程廠商依契約提供之備品 | E121: 1.廠牌：OTIS。2.型號：Rear Outer door T-T 900。3.用途：適用環狀線OTIS電梯。4.規格：(1)含左、右門板。(2)材質：304髮紋不銹鋼。(3)厚度：1.5mm±0.1mm。 | F121: EA | G121: 環狀線南機廠大型物料倉庫 | H121: YSD.02.02.B.02 | I121: 1
A122: 不可修件 | B122: Y5.14.0023.LO | C122: 乙太網路介面卡 | D122: X 工程廠商依契約提供之備品 | E122: 1.廠牌：阿爾卡特朗訊ALCATEL-LUCENT 2.型號：3AL81915BA 3.用途：FOT替換性備品 | F122: EA | G122: 環狀線南機廠空調倉庫 | H122: YSAC1.03.07.D | I122: 0
A123: 可修件 | B123: 32.AP.0005.BB | C123: BPI界面轉換器 | D123: X 工程廠商依契約提供之備品 | E123: 一、廠牌: BBR 二、型號: PZB-226 BPI 三、規格: 處理器AMD geode LX800、快閃儲存器8 G、工作記憶體128M RAM | F123: PC | G123: 淡海輕軌中心倉庫 | H123: DMW3311 | I123: 0
A124: 可修件 | B124: 32.AP.0005.BB | C124: BPI界面轉換器 | D124: X 工程廠商依契約提供之備品 | E124: 一、廠牌: BBR 二、型號: PZB-226 BPI 三、規格: 處理器AMD geode LX800、快閃儲存器8 G、工作記憶體128M RAM | F124: PC | G124: 淡海輕軌中心倉庫 | H124: DMW3311 | I124: 0
A125: 可修件 | B125: 32.AP.0005.BB | C125: BPI界面轉換器 | D125: X 工程廠商依契約提供之備品 | E125: 一、廠牌: BBR 二、型號: PZB-226 BPI 三、規格: 處理器AMD geode LX800、快閃儲存器8 G、工作記憶體128M RAM | F125: PC | G125: 安坑輕軌分存站 | H125: ATS0002 | I125: 1
A126: 代管捷運局之工具/儀器 | B126: 95.01.0012.KW | C126: 梅開扳手(10 mm) | D126: X 工程廠商依契約提供之備品 | E126: 梅開扳手(10 mm) | F126: PC | G126: 淡海輕軌中心倉庫 | H126: DMW1311 | I126: 20
... A131: 不可修件 | B131: 35.28.0007.AV | C131: IP電話機 | D131: X 工程廠商依契約提供之備品 | E131: TEL電話系統使用 | F131: PC | G131: 淡海輕軌中心倉庫 | H131: DMW3112 | I131: 10
A132: 時限品 | B132: YA.II.0008.LO | C132: 傳動皮帶(SPZ-1180) | D132: X 工程廠商依契約提供之備品 | E132: 廠牌:Continental型號:SPZ-1180*2條產品標示之保存期限：自製造日起至少 60 個月 | F132: ST | G132: 環狀線南機廠主倉庫 | H132: YSC.03.14.B.01.03.03.T | I132: 0 | J132: 2024/02/01
A133: 不可修件 | B133: Y3.DC.0028.LO | C133: LED指示燈，紅色 | D133: X 工程廠商依契約提供之備品 | E133: 1.廠牌：DOMO 2.型號：HD22（Red) 3.環狀線專屬用料 | F133: PC | G133: 環狀線南機廠空調倉庫 | H133: YSAC1.01.03.B.02 | I133: 3
A134: 不可修件 | B134: Y9.P4.0003.CF | C134: PAM印表機變壓器 | D134: X 工程廠商依契約提供之備品 | E134: 廠牌:EPSON 型號:M235B 規格:輸出24V/1.5A | F134: EA | G134: 運務中心票務課現場料架-板橋Y15 | H134: YSKF.02.03.C | I134: 1
A135: 不可修件 | B135: Y9.P4.0003.CF | C135: PAM印表機變壓器 | D135: X 工程廠商依契約提供之備品 | E135: 廠牌:EPSON 型號:M235B 規格:輸出24V/1.5A | F135: EA | G135: 環狀線南機廠空調倉庫 | H135: YSAC1.04.03.F.01 | I135: 0
A136: 時限品 | B136: YC.A1.0054.LR | C136: 液壓油 | D136: X 工程廠商依契約提供之備品 | E136: 料號 : 76192-1 AVIA Syntofluid PE-B 32L 規格:20公升 | F136: PL | G136: 環狀線南機廠特殊品倉庫 | H136: YSK.03.01.D.01.02.T | I136: 0 | J136: 2032/01/14
A137: 時限品 | B137: YC.A1.0054.LR | C137: 液壓油 | D137: X 工程廠商依契約提供之備品 | E137: 料號 : 76192-1 AVIA Syntofluid PE-B 32L 規格:20公升 | F137: PL | G137: 環狀線南機廠特殊品倉庫 | H137: YSK.03.02.C.01.01.T2 | I137: 1 | J137: 2032/01/14
A138: 不可修件 | B138: 48.FF.0070.KU | C138: 燈具L5 | D138: X 工程廠商依契約提供之備品 | E138: 1.廠牌:凱優牌 2.型號:L5 3.規格:LED崁燈42W/4300流明 | F138: EA | G138: 安坑輕軌分存站 | H138: ATS0004 | I138: 3
A139: 不可修件 | B139: 94.20.0028.YS | C139: 絕緣毯 | D139: N 採購品 | E139: 1.耐電壓：20kV 2.材質：橡膠 3.使用電壓：17kV | F139: ST | G139: 淡海輕軌中心倉庫 | H139: DMS0000 | I139: 1
A140: 不可修件 | B140: Y1.BC.0009.LO | C140: 六角螺絲 M20x130 | D140: N 採購品 | E140: 1、廠牌：BOSSARD。 2、型號：BN 57。 3、規格：M20x130。 | F140: EA | G140: 環狀線南機廠大型物料倉庫 | H140: YSD.G | I140: 0
A141: 不可修件 | B141: Y1.BC.0009.LO | C141: 六角螺絲 M20x130 | D141: N 採購品 | E141: 1、廠牌：BOSSARD。 2、型號：BN 57。 3、規格：M20x130。 | F141: EA | G141: 環狀線南機廠主倉庫 | H141: YSC.03.11.A.01 | I141: 100
A142: 不可修件 | B142: Y1.PV.0036.LO | C142: 馬達電刷 | D142: N 採購品 | E142: 1、廠牌：Microelettrica 或 Knorr-Bremse。 2、型號：62290735B01。 | F142: PC | G142: 環狀線南機廠大型物料倉庫 | H142: YSD.03.02.A.01 | I142: 0
A143: 不可修件 | B143: Y1.PV.0036.LO | C143: 馬達電刷 | D143: N 採購品 | E143: 1、廠牌：Microelettrica 或 Knorr-Bremse。 2、型號：62290735B01。 | F143: PC | G143: 環狀線南機廠空調倉庫 | H143: YSAC1.04.02.D | I143: 44
A144: 不可修件 | B144: Y3.PR.0009.LO | C144: 保護電驛(L30線路/B30匯流排差動/電源模組) | D144: X 工程廠商依契約提供之備品 | E144: 1.廠牌：GE 2.型號：UR RHV 3.規格：161kV(BSS)/22kV(BSS,PPSS) 4.環狀線專屬用料 | F144: EA | G144: 環狀線南機廠空調倉庫 | H144: YSAC1.11.01.B | I144: 0
A145: 不可修件 | B145: Y6.16.0014.LO | C145: 支距墊鈑 | D145: X 工程廠商依契約提供之備品 | E145: 廠牌：中鐵山橋 規格：719×180×25 | F145: PC | G145: 環狀線南機廠倉庫露儲區 | H145: YSS.07 | I145: 2
A146: 不可修件 | B146: Y1.KT.0083.LO | C146: 3M長期抗UV彩繪PVC-B CAR-C6 | D146: X 工程廠商依契約提供之備品 | E146: 廠牌:爵士影像事業有限公司，規格: PVC-B CAR-C6，說明:列車外裝公共藝術貼紙 | F146: PC | G146: 環狀線南機廠空調倉庫 | H146: YSAC1.09.04.F | I146: 1
A147: 工具/儀器 | B147: 95.03.0040.TO | C147: 歐式彎咀外扣環鉗組 | D147: N 採購品 | E147: 品牌型號TOPTUL DCAA1207 規格：開口19-60mm | F147: PC | G147: 淡海輕軌中心倉庫 | H147: DMS8888 | I147: 0
A148: 工具/儀器 | B148: 95.03.0040.TO | C148: 歐式彎咀外扣環鉗組 | D148: U 零值堪用品 | E148: 品牌型號TOPTUL DCAA1207 規格：開口19-60mm | F148: PC | G148: 淡海輕軌中心倉庫 | H148: DMS0000 | I148: 2
A149: 不可修件 | B149: 39.06.0008.AB | C149: CS ON-OFF PULL TO LOCK | D149: X 工程廠商依契約提供之備品 | E149: 直流供電設備使用 | F149: PC | G149: 安坑輕軌中心倉庫 | H149: AMW1322 | I149: 1
... A165: 不可修件 | B165: YC.A1.0080.LR | C165: 模塊 | D165: X 工程廠商依契約提供之備品 | E165: 料號 : 73656 ET 200SP BU bridged with AUX | F165: PC | G165: 環狀線南機廠主倉庫 | H165: YSC.03.06.D.02.01 | I165: 1
A166: 時限品 | B166: Y1.TW.0024.LO | C166: O型環(610型軸箱前蓋板#100) | D166: X 工程廠商依契約提供之備品 | E166: 1、廠牌：NOK，型號：CO0553A。2、產品標示之保存期限：自製造日起至少 120 個月。3、包裝方式：每包不超過100件為1包。 | F166: EA | G166: 環狀線南機廠空調倉庫 | H166: YSAC1.08.04.E.04.T | I166: 1120 | J166: 2031/08/30
A167: 不可修件 | B167: YA.HI.0041.LO | C167: 風扇軸承 | D167: X 工程廠商依契約提供之備品 | E167: 廠牌:Koyo 型號:6310ZZ | F167: PC | G167: 環狀線南機廠主倉庫 | H167: YSC.02.11.A.01 | I167: 19
A168: 不可修件 | B168: YA.HI.0041.LO | C168: 風扇軸承 | D168: X 工程廠商依契約提供之備品 | E168: 廠牌:Koyo 型號:6310ZZ | F168: PC | G168: 環狀線南機廠主倉庫 | H168: YSC.02.11.E.02 | I168: 0
A169: 不可修件 | B169: 94.14.0012.LO | C169: 自熔接修補帶-灰 | D169: N 採購品 | E169: 魔力自熔接修補帶-灰2.54x305cm。報廢不需繳回 | F169: EA | G169: 環狀線南機廠大型物料倉庫 | H169: YSD.01.02.A.02 | I169: 22
A170: 不可修件 | B170: 94.14.0012.LO | C170: 自熔接修補帶-灰 | D170: N 採購品 | E170: 魔力自熔接修補帶-灰2.54x305cm。報廢不需繳回 | F170: EA | G170: 環狀線南機廠大型物料倉庫 | H170: YSD.G | I170: 0
A171: 不可修件 | B171: 94.14.0012.LO | C171: 自熔接修補帶-灰 | D171: N 採購品 | E171: 魔力自熔接修補帶-灰2.54x305cm。報廢不需繳回 | F171: EA | G171: 環狀線南機廠大型物料倉庫 | H171: YSD.G | I171: 0
A172: 不可修件 | B172: Y6.27.0022.LO | C172: 岔枕 | D172: X 工程廠商依契約提供之備品 | E172: 廠牌：中鐵山橋 規格：4.5M | F172: PC | G172: 環狀線南機廠倉庫露儲區 | H172: YSS.11 | I172: 4
A173: 不可修件 | B173: YD.FF.0048.LO | C173: 日光燈 | D173: X 工程廠商依契約提供之備品 | E173: 1.廠牌：GE 2.型號：MAR/P/C 228EB 3.規格：吸頂式、吊管式、壁掛式 電子安定器 220V 28W*2 IP65 | F173: EA | G173: 環狀線南機廠主倉庫 | H173: YSC.02.14.B.02 | I173: 10
A174: 不可修件 | B174: YC.K1.0016.LO | C174: 內外活接頭(DN15) | D174: X 工程廠商依契約提供之備品 | E174: 材質：不銹鋼SUS 304 規格：DN15（1/2吋），適用於095軌道維修工程車 | F174: BUT | G174: 環狀線南機廠主倉庫 | H174: YSC.01.02.A.01.01 | I174: 1
A175: 可修件 | B175: 37.P4.0001.IN | C175: 液晶顯示模組 | D175: X 工程廠商依契約提供之備品 | E175: 顯示螢幕 | F175: PC | G175: 安坑輕軌分存站 | H175: ATS0005 | I175: 0
A176: 不可修件 | B176: YE.LL.0003.LO | C176: 移動式排水泵 | D176: X 工程廠商依契約提供之備品 | E176: 1.廠牌:有福 2.型號:SL-204 3.出水量=50 公升/分鐘，口徑 50mm | F176: EA | G176: 環狀線南機廠主倉庫 | H176: YSC.02.09.C.02 | I176: 1
A177: 工具/儀器 | B177: 95.42.0058.KT | C177: 1/2"六角氣動起子變換頭 | D177: N 採購品 | E177: 1.六角BIT與BIT接頭專用 2.長度約40mm 3.最大扭力480N-m | F177: ST | G177: 淡海輕軌中心倉庫 | H177: DMS8888 | I177: 0
A178: 工具/儀器 | B178: 95.42.0058.KT | C178: 1/2"六角氣動起子變換頭 | D178: N 採購品 | E178: 1.六角BIT與BIT接頭專用 2.長度約40mm 3.最大扭力480N-m | F178: ST | G178: 淡海輕軌中心倉庫 | H178: DMS0000 | I178: 0
... A206: 不可修件 | B206: Y1.PG.0006.LO | C206: 環狀線電聯車齒輪箱洩油口密封環 | D206: N 採購品 | E206: 1.材質：無氧銅(銅含量99.96%以上)2.尺寸：外徑:32±0.2mm，內徑：26±0.2mm，厚度：2±0.1mm3.表面需平整、不可有翹曲、彎折、變形或毛邊等情形。4.包裝方式：32片/包 | F206: PC | G206: 環狀線南機廠零用金入庫專用儲位 | H206: YSPC | I206: 0
A207: 時限品 | B207: 94.16.0022.LO | C207: 耐高溫固持膠620 | D207: N 採購品 | E207: 1.廠牌：LOCTITE 2.型號：LOCTITE 620 3.容量：50ml | F207: CN | G207: 淡海輕軌中心倉庫 | H207: DMS9998 | I207: 0 | J207: 2027/09/15
A208: 不可修件 | B208: Y1.KT.0069.LO | C208: 3M長期抗UV彩繪PVC-B CAR-B5 | D208: X 工程廠商依契約提供之備品 | E208: 廠牌:爵士影像事業有限公司，規格: PVC-B CAR-B5，說明:列車外裝公共藝術貼紙 | F208: PC | G208: 環狀線南機廠空調倉庫 | H208: YSAC1.10.02.D.01 | I208: 1
A209: 不可修件 | B209: YA.JJ.0007.LO | C209: 可清洗式空氣過濾網 | D209: X 工程廠商依契約提供之備品 | E209: 廠牌:鑫國 規格:5*200*800尼龍濾網 | F209: EA | G209: 環狀線南機廠主倉庫 | H209: YSC.02.13.E.01 | I209: 20
A210: 不可修件 | B210: YA.HH.0014.LO | C210: 風扇軸承 | D210: X 工程廠商依契約提供之備品 | E210: 廠牌：FYH+ADP 型號：UKP212J+H2312 | F210: ST | G210: 環狀線南機廠主倉庫 | H210: YSC.02.08.B.01 | I210: 2
A211: 不可修件 | B211: Y1.KT.0141.LO | C211: 3M長期抗UV彩繪PVC-D CAR-A2 | D211: X 工程廠商依契約提供之備品 | E211: 廠牌:爵士影像事業有限公司，規格: PVC-D CAR-A2，說明:列車外裝公共藝術貼紙 | F211: PC | G211: 環狀線南機廠空調倉庫 | H211: YSAC1.10.03.D.02 | I211: 1
A212: 不可修件 | B212: Y1.VH.0013.LO | C212: 空調新鮮空氣柵門 | D212: X 工程廠商依契約提供之備品 | E212: 廠牌：WUXI，型號：20170110010 或 廠牌：HRI，型號：AU821727 | F212: EA | G212: 環狀線南機廠大型物料倉庫 | H212: YSD.G | I212: 0
A213: 不可修件 | B213: Y1.VH.0013.LO | C213: 空調新鮮空氣柵門 | D213: X 工程廠商依契約提供之備品 | E213: 廠牌：WUXI，型號：20170110010 或 廠牌：HRI，型號：AU821727 | F213: EA | G213: 環狀線南機廠大型物料倉庫 | H213: YSD.02.02.A.02 | I213: 0
A214: 不可修件 | B214: 50.KT.0124.LK | C214: 車輛內側板 | D214: X 工程廠商依契約提供之備品 | E214: ceiling long(13222.0131) | F214: PC | G214: 安坑輕軌分存站 | H214: ATS0001 | I214: 2
A215: 不可修件 | B215: Y5.12.0028.LO | C215: 槍型網路攝影機(IB9387-HT) | D215: X 工程廠商依契約提供之備品 | E215: 1.廠牌：VIVOTEK。2.型號：IB9387-HT。3. 攝像元件採用1/3吋5百萬畫素循序掃描影像感應器。4. 提供1個10/100Base-T RJ45乙太網路埠。5. 電源：具PoE(IEEE 802.3af)標準及12VDC輸入。 6.須可安裝使用於文湖線文山段既有CCTV系統。 | F215: EA | G215: 車電中心號通課現場料架-南機廠一區 | H215: YSKA.H4 | I215: 0
A216: 不可修件 | B216: 50.EP.0021.EA | C216: LED指示燈 | D216: X 工程廠商依契約提供之備品 | E216: 無架空線區間指示燈 | F216: PC | G216: 淡海輕軌中心倉庫 | H216: DMW4622 | I216: 1
A217: 不可修件 | B217: 50.EP.0021.EA | C217: LED指示燈 | D217: X 工程廠商依契約提供之備品 | E217: 無架空線區間指示燈 | F217: PC | G217: 安坑輕軌中心倉庫 | H217: AMW2611 | I217: 1
A218: 不可修件 | B218: 48.HH.0001.TO | C218: 揚聲器 | D218: X 工程廠商依契約提供之備品 | E218: (崁頂式,L級)6W | F218: PC | G218: 安坑輕軌分存站 | H218: ATS0004 | I218: 4
A219: 可修件 | B219: Y1.PV.0006.LO | C219: 斷路器LTHS320(推進) | D219: N 採購品 | E219: 廠牌：HRI，型號：211VK00732B03 或 廠牌：MICROELETTRICA，型號：LTHS03201013800 | F219: EA | G219: 環狀線南機廠大型物料倉庫 | H219: YSD.03.02.A.01 | I219: 0
... A225: 可修件 | B225: Y9.P9.0001.CF | C225: PAM顧客顯示器 | D225: X 工程廠商依契約提供之備品 | E225: 廠牌:MiTAC 型號:TCL-PAM PID | F225: EA | G225: 環狀線南機廠空調倉庫 | H225: YSAC1.10.01.A | I225: 0
A226: 時限品 | B226: Y1.CM.0003.LO | C226: 聯結器潤滑油脂 | D226: X 工程廠商依契約提供之備品 | E226: 1.廠牌:AUTOL2.型號：TOP 20003.容量：400ml/條4.產品標示之保存期限：自製造日起至少36個月 | F226: EA | G226: 環狀線南機廠大型物料倉庫 | H226: YSD.01.03.A.02.11.T | I226: 0 | J226: 2025/07/16
A227: 時限品 | B227: Y1.CM.0003.LO | C227: 聯結器潤滑油脂 | D227: X 工程廠商依契約提供之備品 | E227: 1.廠牌:AUTOL2.型號：TOP 20003.容量：400ml/條4.產品標示之保存期限：自製造日起至少36個月 | F227: EA | G227: 環狀線南機廠大型物料倉庫 | H227: YSD.01.04.E.03.T | I227: 0 | J227: 2025/07/16
A228: 時限品 | B228: Y1.CM.0003.LO | C228: 聯結器潤滑油脂 | D228: N 採購品 | E228: 1.廠牌:AUTOL2.型號：TOP 20003.容量：400ml/條4.產品標示之保存期限：自製造日起至少36個月 | F228: EA | G228: 環狀線南機廠大型物料倉庫 | H228: YSD.G | I228: 0 | J228: 2030/05/17
A229: 時限品 | B229: Y1.CM.0003.LO | C229: 聯結器潤滑油脂 | D229: N 採購品 | E229: 1.廠牌:AUTOL2.型號：TOP 20003.容量：400ml/條4.產品標示之保存期限：自製造日起至少36個月 | F229: EA | G229: 環狀線南機廠大型物料倉庫 | H229: YSD.01.03.A.02.01.T | I229: 12 | J229: 2030/05/17
A230: 不可修件 | B230: Y1.PV.0017.HI | C230: 接地迴路線纜-1 | D230: X 工程廠商依契約提供之備品 | E230: 廠牌：HRI，型號：013158EA01 | F230: ST | G230: 環狀線南機廠大型物料倉庫 | H230: YSD.03.03.A.01 | I230: 48
A231: 不可修件 | B231: 39.17.0014.TP | C231: 止回閥 | D231: X 工程廠商依契約提供之備品 | E231: 液壓系統適用 | F231: PC | G231: 淡海輕軌中心倉庫 | H231: DMW1321 | I231: 1
A232: 不可修件 | B232: 39.17.0014.TP | C232: 止回閥 | D232: X 工程廠商依契約提供之備品 | E232: 液壓系統適用 | F232: PC | G232: 安坑輕軌中心倉庫 | H232: AMW1721 | I232: 2
A233: 不可修件 | B233: Y6.11.0017.LO | C233: 組裝轍岔 | D233: X 工程廠商依契約提供之備品 | E233: 廠牌：中鐵山橋 規格：7號右開 | F233: ST | G233: 環狀線南機廠倉庫露儲區 | H233: YSS.07 | I233: 1
A234: 不可修件 | B234: YC.A1.0060.LR | C234: 保險絲 | D234: X 工程廠商依契約提供之備品 | E234: 料號 : 38308 D01, 10A, gL/gG, 400V | F234: PC | G234: 環狀線南機廠主倉庫 | H234: YSC.03.08.D.01.02 | I234: 3
A235: 不可修件 | B235: 39.59.0019.TP | C235: 按鈕 | D235: X 工程廠商依契約提供之備品 | E235: 操控台適用 | F235: PC | G235: 淡海輕軌中心倉庫 | H235: DMW1331 | I235: 1
A236: 不可修件 | B236: 39.59.0019.TP | C236: 按鈕 | D236: X 工程廠商依契約提供之備品 | E236: 操控台適用 | F236: PC | G236: 安坑輕軌中心倉庫 | H236: AMW1522 | I236: 1
A237: 代管捷運局之工具/儀器 | B237: 95.01.0034.FA | C237: 公制套筒組(套筒頭3/4吋) | D237: X 工程廠商依契約提供之備品 | E237: 套筒(套筒頭3/4吋) | F237: PC | G237: 安坑輕軌分存站 | H237: ATS9999 | I237: 0
A238: 不可修件 | B238: Y6.27.0034.LO | C238: 道岔減震器III型 | D238: X 工程廠商依契約提供之備品 | E238: 廠牌：中鐵山橋 規格：III型減震器 | F238: PC | G238: 環狀線南機廠倉庫露儲區 | H238: YSS.10.24 | I238: 6
A239: 不可修件 | B239: Y6.27.0034.LO | C239: 道岔減震器III型 | D239: X 工程廠商依契約提供之備品 | E239: 廠牌：中鐵山橋 規格：III型減震器 | F239: PC | G239: 環狀線南機廠倉庫露儲區 | H239: YSS.10.01 | I239: 4
A240: 不可修件 | B240: Y6.27.0034.LO | C240: 道岔減震器III型 | D240: X 工程廠商依契約提供之備品 | E240: 廠牌：中鐵山橋 規格：III型減震器 | F240: PC | G240: 環狀線南機廠倉庫露儲區 | H240: YSS.10.22 | I240: 4
A241: 不可修件 | B241: Y6.27.0034.LO | C241: 道岔減震器III型 | D241: X 工程廠商依契約提供之備品 | E241: 廠牌：中鐵山橋 規格：III型減震器 | F241: PC | G241: 環狀線南機廠倉庫露儲區 | H241: YSS.10.05 | I241: 4
... A253: 不可修件 | B253: IS.RV.0004.LO | C253: 反光背心S | D253: N 採購品 | E253: S | F253: PC | G253: 安坑輕軌中心倉庫 | H253: AMW5111 | I253: 10
A254: 時限品 | B254: 94.01.0001.AF | C254: 調合百合白油漆 | D254: N 採購品 | E254: 包裝容量：1加侖/罐 | F254: CN | G254: 淡海輕軌危險物品倉庫 | H254: DHL0301 | I254: 6 | J254: 2026/05/07
A255: 不可修件 | B255: YA.GG.0028.LO | C255: 馬達軸承(5.5~15仟瓦)(板橋公車站及轉運站專屬用料) | D255: X 工程廠商依契約提供之備品 | E255: 1.廠牌:NTN 2.型號或規格:6308ZZ 3.此料號為交通局財產。 4.僅用於板橋公車站及轉運站故障維修使用。 | F255: EA | G255: 環狀線南機廠空調倉庫 | H255: YSAC1.10.05.C.01 | I255: 1
A256: 不可修件 | B256: Y1.EI.0028.LO | C256: 硬碟(DVR) | D256: X 工程廠商依契約提供之備品 | E256: 1.廠牌：Western Digital 2.型號：WD10JUCT 3.容量：1TB | F256: EA | G256: 環狀線南機廠空調倉庫 | H256: YSAC1.08.01.D | I256: 36
A257: 不可修件 | B257: Y1.BE.0027.KB | C257: 液壓控制單元限制閥(#T719) | D257: X 工程廠商依契約提供之備品 | E257: 廠牌：KNORR-BREMSE 型號：I86874 | F257: EA | G257: 環狀線南機廠空調倉庫 | H257: YSAC1.04.06.E.01 | I257: 2
...

Sheet 請購點公式
A1: 請購點（Reorder Point, ROP）模板
A3: 這份模板將依下式自動計算請購點：
A4: ROP = d × T + Z × σd × √T
A5: 其中：
A6: d = 年使用量U / 年天數W（可用365或工作天數250）
A7: T = 交貨期 (L)+ 採購前置時間(P)
A8: Z：由安全等級(1~4)對應的服務水準Z值（見「參數」頁）
A9: σd = 0.25 × d（CV為需求變異係數，可在「參數」頁設定預設值）
A11: C = 是否為市售之指示（市售=0、非市售=1）
A12: 若交期 L > 門檻：視為非市售 (C=1)，啟動風險係數 r。
A13: 若交期 L <門檻：視為市售 (C=0)。
A14: 門檻初始設計60天
... A16: 3) 系統將自動計算日需求、有效等待時間T、安全庫存、請購點(ROP)。

Sheet 參數
A1: 項目 | B1: 值 | D1: 安全等級 | E1: 服務水準(%) | F1: Z值
A2: 年天數 W（天） | B2: 365 | D2: 1 | E2: 90 | F2: 1.28
A3: 非市售風險係數 r | B3: 0.3 | D3: 2 | E3: 95 | F3: 1.65
A4: 預設需求變異係數 CV | B4: 0.25 | D4: 3 | E4: 97.5 | F4: 1.96
D5: 4 | E5: 99 | F5: 2.33

Sheet 請購點計算
A1: 料號/品名 | B1: 年使用量 U(件/年) | C1: 年天數 W(天) | D1: 日需求 d(件/天) | E1: 交貨期 L(天) | F1: 採購前置時間 P(天) | G1: 安全等級 SL(1~4) | H1: Z值 | I1: 市售/非市售 | J1: 非市售風險係數 r | K1: 非市售指示 C | L1: 需求變異係數 CV | M1: 日需求標準差 σd | N1: 有效等待時間 T(天) | O1: 安全庫存 SS | P1: 請購點 ROP(件)
A2: =整合資料!$B$2 -> 電動起子馬達碳刷/廠牌：BOSCH，型號：2609199169 | B2: =整合資料!$AI$2 -> 2 | C2: =參數!$B$2 -> 365 | D2: =IFERROR(B2/C2,0) -> 0.0054794521 | E2: =整合資料!$AO$2 -> 0 | F2: =整合資料!$AP$2 -> 30 | G2: =整合資料!$AQ$2 -> 2 | H2: =IFERROR(VLOOKUP(G2,SL_Z_Table,3,FALSE),0) -> 1.645 | I2: =IF(E2>60,"非市售","市售") -> 市售 | J2: =參數!$B$3 -> 0.3 | K2: =IF(I2="非市售",1,0) -> 0 | L2: =參數!$B$4 -> 0.25 | M2: =L2*D2 -> 0.001369863 | N2: =E2*(1+J2*K2)+F2 -> 30 | O2: =H2*M2*SQRT(N2) -> 0.012342515 | P2: =ROUNDUP(D2*N2+O2,0) -> 1
A3: =整合資料!$B$3 -> 油漆筆(白)/白色 | B3: =整合資料!$AI$3 -> 33 | C3: =參數!$B$2 -> 365 | D3: =IFERROR(B3/C3,0) -> 0.090410959 | E3: =整合資料!$AO$3 -> 0 | F3: =整合資料!$AP$3 -> 30 | G3: =整合資料!$AQ$3 -> 3 | H3: =IFERROR(VLOOKUP(G3,SL_Z_Table,3,FALSE),0) -> 1.96 | I3: =IF(E3>60,"非市售","市售") -> 市售 | J3: =參數!$B$3 -> 0.3 | K3: =IF(I3="非市售",1,0) -> 0 | L3: =參數!$B$4 -> 0.25 | M3: =L3*D3 -> 0.02260274 | N3: =E3*(1+J3*K3)+F3 -> 30 | O3: =H3*M3*SQRT(N3) -> 0.2426486

Sheet 工作表1
A1: 交貨期(L) | BA1: 料號/品名 | BB1: 年使用量 U(件/年) | BC1: 年天數 W(天) | BD1: 日需求 d(件/天) | BE1: 交貨期 L(天) | BF1: 採購前置時間 P(天) | BG1: 安全等級 SL(1~5) | BH1: Z值 | BI1: 市售/非市售 | BJ1: 非市售風險係數 r | BK1: 非市售指示 C | BL1: 需求變異係數 CV | BM1: 日需求標準差 σd | BN1: 有效等待時間 T(天) | BO1: 安全庫存 SS
A2: 0 | B2: =_xlfn.IFS(A2=0, "0(無資料)", A2<=30, "1~30", A2<=60, "31~60", A2<=90, "61~90", A2<=120, "91~120", A2<=150, "121~150", A2<=180, "151~180", A2<=240, "181~240", A2<=330, "241~330", A2>330, "360以上") -> 0(無資料) | E2: 交貨天數下限 (欄位 E) | F2: 群組名稱 (欄位 F) | BA2: =整合資料!B2 -> 電動起子馬達碳刷/廠牌：BOSCH，型號：2609199169 | BB2: =整合資料!AK2 -> 0 | BC2: =[0]!W -> 365 | BD2: =IFERROR(BB2/BC2,0) -> 0 | BE2: =整合資料!AO2 -> 0 | BF2: =整合資料!AP2 -> 30 | BG2: =整合資料!AQ2 -> 2 | BH2: =IFERROR(VLOOKUP(BG2,SL_Z_Table,3,FALSE),0) -> 1.645 | BI2: =IF(整合資料!AO2>60,"非市售","市售") -> 市售 | BJ2: =參數!$B$3 -> 0.3 | BK2: =IF(BI2="非市售",1,0) -> 0 | BL2: =參數!$B$4 -> 0.25 | BM2: =BL2*BD2 -> 0 | BN2: =BE2*(1+BJ2*BK2)+BF2 -> 30 | BO2: =BH2*BM2*SQRT(BN2) -> 0
A3: 0 | E3: 0 | F3: 0(無資料) | BA3: =整合資料!B3 -> 油漆筆(白)/白色 | BB3: =整合資料!AK3 -> 10 | BC3: =[0]!W -> 365 | BD3: =IFERROR(BB3/BC3,0) -> 0.02739726 | BE3: =整合資料!AO3 -> 0 | BF3: =整合資料!AP3 -> 30 | BG3: =整合資料!AQ3 -> 3 | BH3: =IFERROR(VLOOKUP(BG3,SL_Z_Table,3,FALSE),0) -> 1.96 | BI3: =IF(整合資料!AO3>60,"非市售","市售") -> 市售 | BJ3: =參數!$B$3 -> 0.3 | BK3: =IF(BI3="非市售",1,0) -> 0 | BL3: =參數!$B$4 -> 0.25 | BM3: =BL3*BD3 -> 0.0068493151 | BN3: =BE3*(1+BJ3*BK3)+BF3 -> 30 | BO3: =BH3*BM3*SQRT(BN3) -> 0.073529878
A4: 0 | E4: 1 | F4: 1~30 | BA4: =整合資料!B4 -> 油漆筆(黃)/黃色 | BB4: =整合資料!AK4 -> 0 | BC4: =[0]!W -> 365 | BD4: =IFERROR(BB4/BC4,0) -> 0 | BE4: =整合資料!AO4 -> 0 | BF4: =整合資料!AP4 -> 30 | BG4: =整合資料!AQ4 -> 3 | BH4: =IFERROR(VLOOKUP(BG4,SL_Z_Table,3,FALSE),0) -> 1.96 | BI4: =IF(整合資料!AO4>60,"非市售","市售") -> 市售 | BJ4: =參數!$B$3 -> 0.3 | BK4: =IF(BI4="非市售",1,0) -> 0 | BL4: =參數!$B$4 -> 0.25 | BM4: =BL4*BD4 -> 0 | BN4: =BE4*(1+BJ4*BK4)+BF4 -> 30 | BO4: =BH4*BM4*SQRT(BN4) -> 0
A5: 0 | E5: 31 | F5: 31~60 | BA5: =整合資料!B5 -> 噴漆(白)/1.顏色: 白色 2.容量:400ml/罐(含)以上/CN | BB5: =整合資料!AK5 -> 0 | BC5: =[0]!W -> 365 | BD5: =IFERROR(BB5/BC5,0) -> 0 | BE5: =整合資料!AO5 -> 0 | BF5: =整合資料!AP5 -> 30 | BG5: =整合資料!AQ5 -> 3 | BH5: =IFERROR(VLOOKUP(BG5,SL_Z_Table,3,FALSE),0) -> 1.96 | BI5: =IF(整合資料!AO5>60,"非市售","市售") -> 市售 | BJ5: =參數!$B$3 -> 0.3 | BK5: =IF(BI5="非市售",1,0) -> 0 | BL5: =參數!$B$4 -> 0.25 | BM5: =BL5*BD5 -> 0 | BN5: =BE5*(1+BJ5*BK5)+BF5 -> 30 | BO5: =BH5*BM5*SQRT(BN5) -> 0
A6: 0 | E6: 61 | F6: 61~90 | BA6: =整合資料!B6 -> 噴漆(黑)/1.顏色: 黑色 2.容量:400ml/罐(含)以上/CN | BB6: =整合資料!AK6 -> 0 | BC6: =[0]!W -> 365 | BD6: =IFERROR(BB6/BC6,0) -> 0 | BE6: =整合資料!AO6 -> 0 | BF6: =整合資料!AP6 -> 30 | BG6: =整合資料!AQ6 -> 3 | BH6: =IFERROR(VLOOKUP(BG6,SL_Z_Table,3,FALSE),0) -> 1.96 | BI6: =IF(整合資料!AO6>60,"非市售","市售") -> 市售 | BJ6: =參數!$B$3 -> 0.3 | BK6: =IF(BI6="非市售",1,0) -> 0 | BL6: =參數!$B$4 -> 0.25 | BM6: =BL6*BD6 -> 0 | BN6: =BE6*(1+BJ6*BK6)+BF6 -> 30 | BO6: =BH6*BM6*SQRT(BN6) -> 0
A7: 0 | E7: 91 | F7: 91~120 | BA7: =整合資料!B7 -> 冷鍍鋅漆/13oz/CN，噴霧式，產品標示之保存期限：自製造日起至少 36 個月 | BB7: =整合資料!AK7 -> 2 | BC7: =[0]!W -> 365 | BD7: =IFERROR(BB7/BC7,0) -> 0.0054794521 | BE7: =整合資料!AO7 -> 0 | BF7: =整合資料!AP7 -> 30 | BG7: =整合資料!AQ7 -> 2 | BH7: =IFERROR(VLOOKUP(BG7,SL_Z_Table,3,FALSE),0) -> 1.645 | BI7: =IF(整合資料!AO7>60,"非市售","市售") -> 市售 | BJ7: =參數!$B$3 -> 0.3 | BK7: =IF(BI7="非市售",1,0) -> 0 | BL7: =參數!$B$4 -> 0.25 | BM7: =BL7*BD7 -> 0.001369863 | BN7: =BE7*(1+BJ7*BK7)+BF7 -> 30 | BO7: =BH7*BM7*SQRT(BN7) -> 0.012342515
A8: 0 | E8: 121 | F8: 121~150 | BA8: =整合資料!B8 -> 蒸餾水/1.適用電瓶加水用，不含金屬導電物 2.包裝方式：5GAL/桶 | BB8: =整合資料!AK8 -> 21 | BC8: =[0]!W -> 365 | BD8: =IFERROR(BB8/BC8,0) -> 0.057534247 | BE8: =整合資料!AO8 -> 0 | BF8: =整合資料!AP8 -> 30 | BG8: =整合資料!AQ8 -> 2 | BH8: =IFERROR(VLOOKUP(BG8,SL_Z_Table,3,FALSE),0) -> 1.645 | BI8: =IF(整合資料!AO8>60,"非市售","市售") -> 市售 | BJ8: =參數!$B$3 -> 0.3 | BK8: =IF(BI8="非市售",1,0) -> 0 | BL8: =參數!$B$4 -> 0.25 | BM8: =BL8*BD8 -> 0.014383562 | BN8: =BE8*(1+BJ8*BK8)+BF8 -> 30 | BO8: =BH8*BM8*SQRT(BN8) -> 0.12959641
A9: 0 | E9: 151 | F9: 151~180 | BA9: =整合資料!B9 -> 木柄銅絲刷/植毛寬度:20mm±3mm，植毛長度:75mm±5mm，毛長:15mm±3mm，總長220mm以上 | BB9: =整合資料!AK9 -> 20 | BC9: =[0]!W -> 365 | BD9: =IFERROR(BB9/BC9,0) -> 0.054794521 | BE9: =整合資料!AO9 -> 0 | BF9: =整合資料!AP9 -> 30 | BG9: =整合資料!AQ9 -> 2 | BH9: =IFERROR(VLOOKUP(BG9,SL_Z_Table,3,FALSE),0) -> 1.645 | BI9: =IF(整合資料!AO9>60,"非市售","市售") -> 市售 | BJ9: =參數!$B$3 -> 0.3 | BK9: =IF(BI9="非市售",1,0) -> 0 | BL9: =參數!$B$4 -> 0.25 | BM9: =BL9*BD9 -> 0.01369863 | BN9: =BE9*(1+BJ9*BK9)+BF9 -> 30 | BO9: =BH9*BM9*SQRT(BN9) -> 0.12342515
A10: 0 | E10: 181 | F10: 181~240 | BA10: =整合資料!B10 -> 氬氣/充填壓力120kg/c㎡以上，容積6立方米 | BB10: =整合資料!AK10 -> 0 | BC10: =[0]!W -> 365 | BD10: =IFERROR(BB10/BC10,0) -> 0 | BE10: =整合資料!AO10 -> 0 | BF10: =整合資料!AP10 -> 30 | BG10: =整合資料!AQ10 -> 2 | BH10: =IFERROR(VLOOKUP(BG10,SL_Z_Table,3,FALSE),0) -> 1.645 | BI10: =IF(整合資料!AO10>60,"非市售","市售") -> 市售 | BJ10: =參數!$B$3 -> 0.3 | BK10: =IF(BI10="非市售",1,0) -> 0 | BL10: =參數!$B$4 -> 0.25 | BM10: =BL10*BD10 -> 0 | BN10: =BE10*(1+BJ10*BK10)+BF10 -> 30 | BO10: =BH10*BM10*SQRT(BN10) -> 0
A11: 0 | E11: 241 | F11: 241~330 | BA11: =整合資料!B11 -> 氮氣(含瓶身)/1.充填壓力：190kg/c㎡以上，水容積：50L，容積：10立方米。 2.適用氣體名稱：氮氣。 3.接頭型式：CGA580。 4.須含鋼瓶身。 | BB11: =整合資料!AK11 -> 9 | BC11: =[0]!W -> 365 | BD11: =IFERROR(BB11/BC11,0) -> 0.024657534 | BE11: =整合資料!AO11 -> 0 | BF11: =整合資料!AP11 -> 30 | BG11: =整合資料!AQ11 -> 2 | BH11: =IFERROR(VLOOKUP(BG11,SL_Z_Table,3,FALSE),0) -> 1.645 | BI11: =IF(整合資料!AO11>60,"非市售","市售") -> 市售 | BJ11: =參數!$B$3 -> 0.3 | BK11: =IF(BI11="非市售",1,0) -> 0 | BL11: =參數!$B$4 -> 0.25 | BM11: =BL11*BD11 -> 0.0061643836 | BN11: =BE11*(1+BJ11*BK11)+BF11 -> 30 | BO11: =BH11*BM11*SQRT(BN11) -> 0.055541318
A12: 0 | E12: 331 | F12: 360以上 | BA12: =整合資料!B12 -> PVC絕緣膠布(紅色)/紅色 0.2mm*19mm*10m | BB12: =整合資料!AK12 -> 5 | BC12: =[0]!W -> 365 | BD12: =IFERROR(BB12/BC12,0) -> 0.01369863 | BE12: =整合資料!AO12 -> 0 | BF12: =整合資料!AP12 -> 30 | BG12: =整合資料!AQ12 -> 2 | BH12: =IFERROR(VLOOKUP(BG12,SL_Z_Table,3,FALSE),0) -> 1.645 | BI12: =IF(整合資料!AO12>60,"非市售","市售") -> 市售 | BJ12: =參數!$B$3 -> 0.3 | BK12: =IF(BI12="非市售",1,0) -> 0 | BL12: =參數!$B$4 -> 0.25 | BM12: =BL12*BD12 -> 0.0034246575 | BN12: =BE12*(1+BJ12*BK12)+BF12 -> 30 | BO12: =BH12*BM12*SQRT(BN12) -> 0.030856288
A13: 0 | BA13: =整合資料!B13 -> PVC絕緣膠布(黑色)/黑色 0.2mm*19mm 10m | BB13: =整合資料!AK13 -> 9 | BC13: =[0]!W -> 365 | BD13: =IFERROR(BB13/BC13,0) -> 0.024657534 | BE13: =整合資料!AO13 -> 0 | BF13: =整合資料!AP13 -> 30 | BG13: =整合資料!AQ13 -> 2 | BH13: =IFERROR(VLOOKUP(BG13,SL_Z_Table,3,FALSE),0) -> 1.645 | BI13: =IF(整合資料!AO13>60,"非市售","市售") -> 市售 | BJ13: =參數!$B$3 -> 0.3 | BK13: =IF(BI13="非市售",1,0) -> 0 | BL13: =參數!$B$4 -> 0.25 | BM13: =BL13*BD13 -> 0.0061643836 | BN13: =BE13*(1+BJ13*BK13)+BF13 -> 30 | BO13: =BH13*BM13*SQRT(BN13) -> 0.055541318
A14: 0 | BA14: =整合資料!B14 -> PVC絕緣膠布(黃色)/黃色 0.2mm*19mm*10m | BB14: =整合資料!AK14 -> 1 | BC14: =[0]!W -> 365 | BD14: =IFERROR(BB14/BC14,0) -> 0.002739726 | BE14: =整合資料!AO14 -> 0 | BF14: =整合資料!AP14 -> 30 | BG14: =整合資料!AQ14 -> 2 | BH14: =IFERROR(VLOOKUP(BG14,SL_Z_Table,3,FALSE),0) -> 1.645 | BI14: =IF(整合資料!AO14>60,"非市售","市售") -> 市售 | BJ14: =參數!$B$3 -> 0.3 | BK14: =IF(BI14="非市售",1,0) -> 0 | BL14: =參數!$B$4 -> 0.25 | BM14: =BL14*BD14 -> 0.00068493151 | BN14: =BE14*(1+BJ14*BK14)+BF14 -> 30 | BO14: =BH14*BM14*SQRT(BN14) -> 0.0061712576
A15: 0 | BA15: =整合資料!B15 -> PVC絕緣膠布(白色)/白色 0.2mm*19mm*10m | BB15: =整合資料!AK15 -> 4 | BC15: =[0]!W -> 365 | BD15: =IFERROR(BB15/BC15,0) -> 0.010958904 | BE15: =整合資料!AO15 -> 0 | BF15: =整合資料!AP15 -> 30 | BG15: =整合資料!AQ15 -> 2 | BH15: =IFERROR(VLOOKUP(BG15,SL_Z_Table,3,FALSE),0) -> 1.645 | BI15: =IF(整合資料!AO15>60,"非市售","市售") -> 市售 | BJ15: =參數!$B$3 -> 0.3 | BK15: =IF(BI15="非市售",1,0) -> 0 | BL15: =參數!$B$4 -> 0.25 | BM15: =BL15*BD15 -> 0.002739726 | BN15: =BE15*(1+BJ15*BK15)+BF15 -> 30 | BO15: =BH15*BM15*SQRT(BN15) -> 0.02468503
A16: 0 | BA16: =整合資料!B16 -> PVC絕緣膠布(綠色)/綠色 0.2mm*19mm*10m | BB16: =整合資料!AK16 -> 2 | BC16: =[0]!W -> 365 | BD16: =IFERROR(BB16/BC16,0) -> 0.0054794521 | BE16: =整合資料!AO16 -> 0 | BF16: =整合資料!AP16 -> 30 | BG16: =整合資料!AQ16 -> 2 | BH16: =IFERROR(VLOOKUP(BG16,SL_Z_Table,3,FALSE),0) -> 1.645 | BI16: =IF(整合資料!AO16>60,"非市售","市售") -> 市售 | BJ16: =參數!$B$3 -> 0.3 | BK16: =IF(BI16="非市售",1,0) -> 0 | BL16: =參數!$B$4 -> 0.25 | BM16: =BL16*BD16 -> 0.001369863 | BN16: =BE16*(1+BJ16*BK16)+BF16 -> 30 | BO16: =BH16*BM16*SQRT(BN16) -> 0.012342515
A17: 0 | BA17: =整合資料!B17 -> 止洩帶/一般管路防漏用，規格：厚度：0.1mm、寬度：13mm、每捲長度：15m以上 | BB17: =整合資料!AK17 -> 16 | BC17: =[0]!W -> 365 | BD17: =IFERROR(BB17/BC17,0) -> 0.043835616 | BE17: =整合資料!AO17 -> 0 | BF17: =整合資料!AP17 -> 30 | BG17: =整合資料!AQ17 -> 2 | BH17: =IFERROR(VLOOKUP(BG17,SL_Z_Table,3,FALSE),0) -> 1.645 | BI17: =IF(整合資料!AO17>60,"非市售","市售") -> 市售 | BJ17: =參數!$B$3 -> 0.3 | BK17: =IF(BI17="非市售",1,0) -> 0 | BL17: =參數!$B$4 -> 0.25 | BM17: =BL17*BD17 -> 0.010958904 | BN17: =BE17*(1+BJ17*BK17)+BF17 -> 30 | BO17: =BH17*BM17*SQRT(BN17) -> 0.098740121
A18: 0 | BA18: =整合資料!B18 -> 矽利康(施敏打硬，黑)/1、廠牌：CEMEDINE ，型號：SUPER X NO.8008，容量:333ml/條，顏色：黑。 2、保存期限：自製造日起至少12個月。 | BB18: =整合資料!AK18 -> 1 | BC18: =[0]!W -> 365 | BD18: =IFERROR(BB18/BC18,0) -> 0.002739726 | BE18: =整合資料!AO18 -> 0 | BF18: =整合資料!AP18 -> 30 | BG18: =整合資料!AQ18 -> 2 | BH18: =IFERROR(VLOOKUP(BG18,SL_Z_Table,3,FALSE),0) -> 1.645 | BI18: =IF(整合資料!AO18>60,"非市售","市售") -> 市售 | BJ18: =參數!$B$3 -> 0.3 | BK18: =IF(BI18="非市售",1,0) -> 0 | BL18: =參數!$B$4 -> 0.25 | BM18: =BL18*BD18 -> 0.00068493151 | BN18: =BE18*(1+BJ18*BK18)+BF18 -> 30 | BO18: =BH18*BM18*SQRT(BN18) -> 0.0061712576
A19: 0 | BA19: =整合資料!B19 -> 熱縮套管(10.4mm)/1、廠牌：KSS，型號：F32-10 。 2、尺寸：收縮前內徑10.4mm±0.4mm。 3、內徑收縮率50%以上。 4、顏色：黑色。 5、包裝：50m/捲。 | BB19: =整合資料!AK19 -> 2 | BC19: =[0]!W -> 365 | BD19: =IFERROR(BB19/BC19,0) -> 0.0054794521 | BE19: =整合資料!AO19 -> 0 | BF19: =整合資料!AP19 -> 30 | BG19: =整合資料!AQ19 -> 2 | BH19: =IFERROR(VLOOKUP(BG19,SL_Z_Table,3,FALSE),0) -> 1.645 | BI19: =IF(整合資料!AO19>60,"非市售","市售") -> 市售 | BJ19: =參數!$B$3 -> 0.3 | BK19: =IF(BI19="非市售",1,0) -> 0 | BL19: =參數!$B$4 -> 0.25 | BM19: =BL19*BD19 -> 0.001369863 | BN19: =BE19*(1+BJ19*BK19)+BF19 -> 30 | BO19: =BH19*BM19*SQRT(BN19) -> 0.012342515
A20: 0 | BA20: =整合資料!B20 -> 熱縮套管(3.5mm)/1、廠牌：KSS，型號：F32-3。 2、尺寸：收縮前內徑3.5mm±0.3mm。 3、內徑收縮率50%以上。 4、顏色：黑色。 5、包裝：200m/捲。 | BB20: =整合資料!AK20 -> 2 | BC20: =[0]!W -> 365 | BD20: =IFERROR(BB20/BC20,0) -> 0.0054794521 | BE20: =整合資料!AO20 -> 0 | BF20: =整合資料!AP20 -> 30 | BG20: =整合資料!AQ20 -> 2 | BH20: =IFERROR(VLOOKUP(BG20,SL_Z_Table,3,FALSE),0) -> 1.645 | BI20: =IF(整合資料!AO20>60,"非市售","市售") -> 市售 | BJ20: =參數!$B$3 -> 0.3 | BK20: =IF(BI20="非市售",1,0) -> 0 | BL20: =參數!$B$4 -> 0.25 | BM20: =BL20*BD20 -> 0.001369863 | BN20: =BE20*(1+BJ20*BK20)+BF20 -> 30 | BO20: =BH20*BM20*SQRT(BN20) -> 0.012342515
A21: 0 | BA21: =整合資料!B21 -> PVC絕緣膠布(藍色)/藍色 0.2mm*19mm*10m。 | BB21: =整合資料!AK21 -> 2 | BC21: =[0]!W -> 365 | BD21: =IFERROR(BB21/BC21,0) -> 0.0054794521 | BE21: =整合資料!AO21 -> 0 | BF21: =整合資料!AP21 -> 30 | BG21: =整合資料!AQ21 -> 2 | BH21: =IFERROR(VLOOKUP(BG21,SL_Z_Table,3,FALSE),0) -> 1.645 | BI21: =IF(整合資料!AO21>60,"非市售","市售") -> 市售 | BJ21: =參數!$B$3 -> 0.3 | BK21: =IF(BI21="非市售",1,0) -> 0 | BL21: =參數!$B$4 -> 0.25 | BM21: =BL21*BD21 -> 0.001369863 | BN21: =BE21*(1+BJ21*BK21)+BF21 -> 30 | BO21: =BH21*BM21*SQRT(BN21) -> 0.012342515
A22: 0 | BA22: =整合資料!B22 -> 凡士林(潤滑用)/容量:1kg/瓶 | BB22: =整合資料!AK22 -> 0 | BC22: =[0]!W -> 365 | BD22: =IFERROR(BB22/BC22,0) -> 0 | BE22: =整合資料!AO22 -> 0 | BF22: =整合資料!AP22 -> 30 | BG22: =整合資料!AQ22 -> 2 | BH22: =IFERROR(VLOOKUP(BG22,SL_Z_Table,3,FALSE),0) -> 1.645 | BI22: =IF(整合資料!AO22>60,"非市售","市售") -> 市售 | BJ22: =參數!$B$3 -> 0.3 | BK22: =IF(BI22="非市售",1,0) -> 0 | BL22: =參數!$B$4 -> 0.25 | BM22: =BL22*BD22 -> 0 | BN22: =BE22*(1+BJ22*BK22)+BF22 -> 30 | BO22: =BH22*BM22*SQRT(BN22) -> 0
A23: 0 | BA23: =整合資料!B23 -> 液壓油(SHELL TELLUS S2 MX 46)/1.廠牌：SHELL、型號：TELLUS S2 MX 46。2.包裝方式：209公升/桶。3.產品標示之保存期限：自製造日起至少48 個月。 | BB23: =整合資料!AK23 -> 5 | BC23: =[0]!W -> 365 | BD23: =IFERROR(BB23/BC23,0) -> 0.01369863 | BE23: =整合資料!AO23 -> 0 | BF23: =整合資料!AP23 -> 30 | BG23: =整合資料!AQ23 -> 2 | BH23: =IFERROR(VLOOKUP(BG23,SL_Z_Table,3,FALSE),0) -> 1.645 | BI23: =IF(整合資料!AO23>60,"非市售","市售") -> 市售 | BJ23: =參數!$B$3 -> 0.3 | BK23: =IF(BI23="非市售",1,0) -> 0 | BL23: =參數!$B$4 -> 0.25 | BM23: =BL23*BD23 -> 0.0034246575 | BN23: =BE23*(1+BJ23*BK23)+BF23 -> 30 | BO23: =BH23*BM23*SQRT(BN23) -> 0.030856288
A24: 0 | BA24: =整合資料!B24 -> 除銹潤滑油/具有滲透除銹、潤滑鎖頭、消除因機械磨擦產生雜聲等功能，可作為各類金屬或一般材質零組件的維修保養使用，包裝方式：380ml以上，產品標示之保存期限：自製造日起至少 24 個月 | BB24: =整合資料!AK24 -> 15 | BC24: =[0]!W -> 365 | BD24: =IFERROR(BB24/BC24,0) -> 0.04109589 | BE24: =整合資料!AO24 -> 0 | BF24: =整合資料!AP24 -> 30 | BG24: =整合資料!AQ24 -> 2 | BH24: =IFERROR(VLOOKUP(BG24,SL_Z_Table,3,FALSE),0) -> 1.645 | BI24: =IF(整合資料!AO24>60,"非市售","市售") -> 市售 | BJ24: =參數!$B$3 -> 0.3 | BK24: =IF(BI24="非市售",1,0) -> 0 | BL24: =參數!$B$4 -> 0.25 | BM24: =BL24*BD24 -> 0.010273973 | BN24: =BE24*(1+BJ24*BK24)+BF24 -> 30 | BO24: =BH24*BM24*SQRT(BN24) -> 0.092568864
... A259: 0 | BA259: =整合資料!B259 -> 導熱膏(DC340)/廠牌：DOWSIL或同等品，型號：DC340，容量：142g/條。 | BB259: =整合資料!AK259 -> 3 | BC259: =[0]!W -> 365 | BD259: =IFERROR(BB259/BC259,0) -> 0.0082191781 | BE259: =整合資料!AO259 -> 0 | BF259: =整合資料!AP259 -> 30 | BG259: =整合資料!AQ259 -> 2 | BH259: =IFERROR(VLOOKUP(BG259,SL_Z_Table,3,FALSE),0) -> 1.645 | BI259: =IF(整合資料!AO259>60,"非市售","市售") -> 市售 | BJ259: =參數!$B$3 -> 0.3 | BK259: =IF(BI259="非市售",1,0) -> 0 | BL259: =參數!$B$4 -> 0.25 | BM259: =BL259*BD259 -> 0.0020547945 | BN259: =BE259*(1+BJ259*BK259)+BF259 -> 30 | BO259: =BH259*BM259*SQRT(BN259) -> 0.018513773
A260: 0
A261: 0
A262: 0
A263: 0
A264: 0
A265: 0
A266: 0
A267: 0
A268: 0
A269: 0
A270: 0
A271: 0
... A1300: 540
